Workbook

Sheet Como usar
B2: Controle Financeiro — Darzan Produções
B3: Storymaker & Videomaker · Campinas e região
B5: COMO FUNCIONA
B6: 1. Você só anota | C6: Preencha as abas de lançamento (Trabalhos, Orçamentos, Clientes, Freelancers, Gastos e Equipamentos). O Resumo e a Agenda se calculam sozinhos.
B7: 2. Cores das colunas | C7: Colunas BRANCAS = você digita. Colunas CINZAS = automáticas, não digite nelas. Célula AMARELA no Resumo = ano que você quer ver.
B8: 3. Menus | C8: Várias colunas têm uma setinha com opções (tipo de evento, status...). Para mudar as opções, edite a aba "Listas".
B9: 4. Código do trabalho | C9: Cada trabalho tem um código (T001, T002, T003...). Use o mesmo código em Freelancers e Gastos para o sistema saber de qual trabalho é cada gasto.
B10: 5. Linhas de exemplo | C10: As linhas marcadas com "EXEMPLO" servem só para você ver como funciona. Apague essas linhas (selecione e aperte Delete) antes de começar a usar de verdade.
B12: O QUE ANOTAR EM CADA ABA
B13: Resumo | C13: Seu painel: ganho bruto, lucro, gastos com freelancer, taxa de fechamento de orçamentos, resultados por mês e por tipo de evento.
B14: Agenda | C14: Lista automática dos próximos eventos, puxada da aba Trabalhos (só aparecem datas de hoje em diante).
B15: Trabalhos | C15: Cada evento fechado: data, cliente, tipo, valor cobrado e quanto já recebeu. Freelancers, outros gastos e lucro são calculados.
B16: Orçamentos | C16: TODO orçamento que você passar, fechando ou não. Mude o status para Fechado ou Recusado quando o cliente responder.
B17: Clientes | C17: Contato dos clientes e como te conheceram. O total de trabalhos e quanto cada um já pagou são automáticos.
B18: Freelancers | C18: Cada pagamento a freelancer, com o código do trabalho. Assim você vê quanto gastou com freela em cada trabalho.
B19: Gastos | C19: Despesas do dia a dia: combustível, apps, cursos, anúncios... Se o gasto for de um trabalho específico, coloque o código dele.
B20: Equipamentos | C20: Tudo que você comprou para trabalhar. O Resumo mostra quanto já investiu e quanto do investimento o lucro já pagou.
B21: Listas | C21: As opções dos menus. Pode adicionar novas opções nas linhas vazias.
B23: DICAS
B24: Datas | C24: Digite sempre no formato dia/mês/ano, por exemplo 14/03/2026.
B25: Valores | C25: Digite só o número (ex: 2500 ou 2500,50). O "R$" aparece sozinho.
B26: Lucro | C26: Lucro = ganho bruto − freelancers − outros gastos. Equipamentos ficam separados porque são investimento, não gasto do mês.
B27: Não apague | C27: Não apague colunas nem as linhas de título. Para remover um lançamento, apague só o conteúdo da linha.

Sheet Resumo
B1: Painel financeiro — Darzan Produções
B2: Tudo aqui é automático. Só troque o ano na célula amarela.
B4: Ano que você quer ver: | C4: 2026
B6: Indicador | C6: No ano escolhido | D6: Desde o início | F6: Mês | G6: Ganho bruto | H6: Freelancers | I6: Outros gastos | J6: Lucro | K6: Trabalhos | L6: Orçam. passados | M6: Orçam. fechados
B7: Ganho bruto (valor cobrado) | C7: =SUMIFS(Trabalhos!$G$5:$G$504,Trabalhos!$B$5:$B$504,">="&DATE($C$4,1,1),Trabalhos!$B$5:$B$504,"<"&DATE($C$4+1,1,1)) -> 11600 | D7: =SUM(Trabalhos!$G$5:$G$504) -> 11600 | F7: Janeiro | G7: =SUMIFS(Trabalhos!$G$5:$G$504,Trabalhos!$B$5:$B$504,">="&DATE($C$4,1,1),Trabalhos!$B$5:$B$504,"<"&DATE($C$4,1+1,1)) -> 0 | H7: =SUMIFS(Freelancers!$E$5:$E$504,Freelancers!$A$5:$A$504,">="&DATE($C$4,1,1),Freelancers!$A$5:$A$504,"<"&DATE($C$4,1+1,1)) -> 0 | I7: =SUMIFS(Gastos!$D$5:$D$504,Gastos!$A$5:$A$504,">="&DATE($C$4,1,1),Gastos!$A$5:$A$504,"<"&DATE($C$4,1+1,1)) -> 0 | J7: =G7-H7-I7 -> 0 | K7: =COUNTIFS(Trabalhos!$B$5:$B$504,">="&DATE($C$4,1,1),Trabalhos!$B$5:$B$504,"<"&DATE($C$4,1+1,1)) -> 0 | L7: =COUNTIFS(Orçamentos!$A$5:$A$504,">="&DATE($C$4,1,1),Orçamentos!$A$5:$A$504,"<"&DATE($C$4,1+1,1)) -> 1 | M7: =COUNTIFS(Orçamentos!$A$5:$A$504,">="&DATE($C$4,1,1),Orçamentos!$A$5:$A$504,"<"&DATE($C$4,1+1,1),Orçamentos!$F$5:$F$504,"Fechado") -> 1
B8: Já recebido | C8: =SUMIFS(Trabalhos!$H$5:$H$504,Trabalhos!$B$5:$B$504,">="&DATE($C$4,1,1),Trabalhos!$B$5:$B$504,"<"&DATE($C$4+1,1,1)) -> 8900 | D8: =SUM(Trabalhos!$H$5:$H$504) -> 8900 | F8: Fevereiro | G8: =SUMIFS(Trabalhos!$G$5:$G$504,Trabalhos!$B$5:$B$504,">="&DATE($C$4,2,1),Trabalhos!$B$5:$B$504,"<"&DATE($C$4,2+1,1)) -> 0 | H8: =SUMIFS(Freelancers!$E$5:$E$504,Freelancers!$A$5:$A$504,">="&DATE($C$4,2,1),Freelancers!$A$5:$A$504,"<"&DATE($C$4,2+1,1)) -> 0 | I8: =SUMIFS(Gastos!$D$5:$D$504,Gastos!$A$5:$A$504,">="&DATE($C$4,2,1),Gastos!$A$5:$A$504,"<"&DATE($C$4,2+1,1)) -> 0 | J8: =G8-H8-I8 -> 0 | K8: =COUNTIFS(Trabalhos!$B$5:$B$504,">="&DATE($C$4,2,1),Trabalhos!$B$5:$B$504,"<"&DATE($C$4,2+1,1)) -> 0 | L8: =COUNTIFS(Orçamentos!$A$5:$A$504,">="&DATE($C$4,2,1),Orçamentos!$A$5:$A$504,"<"&DATE($C$4,2+1,1)) -> 1 | M8: =COUNTIFS(Orçamentos!$A$5:$A$504,">="&DATE($C$4,2,1),Orçamentos!$A$5:$A$504,"<"&DATE($C$4,2+1,1),Orçamentos!$F$5:$F$504,"Fechado") -> 0
B9: A receber | C9: =C7-C8 -> 2700 | D9: =D7-D8 -> 2700 | F9: Março | G9: =SUMIFS(Trabalhos!$G$5:$G$504,Trabalhos!$B$5:$B$504,">="&DATE($C$4,3,1),Trabalhos!$B$5:$B$504,"<"&DATE($C$4,3+1,1)) -> 3500 | H9: =SUMIFS(Freelancers!$E$5:$E$504,Freelancers!$A$5:$A$504,">="&DATE($C$4,3,1),Freelancers!$A$5:$A$504,"<"&DATE($C$4,3+1,1)) -> 650 | I9: =SUMIFS(Gastos!$D$5:$D$504,Gastos!$A$5:$A$504,">="&DATE($C$4,3,1),Gastos!$A$5:$A$504,"<"&DATE($C$4,3+1,1)) -> 80 | J9: =G9-H9-I9 -> 2770 | K9: =COUNTIFS(Trabalhos!$B$5:$B$504,">="&DATE($C$4,3,1),Trabalhos!$B$5:$B$504,"<"&DATE($C$4,3+1,1)) -> 1 | L9: =COUNTIFS(Orçamentos!$A$5:$A$504,">="&DATE($C$4,3,1),Orçamentos!$A$5:$A$504,"<"&DATE($C$4,3+1,1)) -> 0 | M9: =COUNTIFS(Orçamentos!$A$5:$A$504,">="&DATE($C$4,3,1),Orçamentos!$A$5:$A$504,"<"&DATE($C$4,3+1,1),Orçamentos!$F$5:$F$504,"Fechado") -> 0
B10: Gastos com freelancers | C10: =SUMIFS(Freelancers!$E$5:$E$504,Freelancers!$A$5:$A$504,">="&DATE($C$4,1,1),Freelancers!$A$5:$A$504,"<"&DATE($C$4+1,1,1)) -> 1150 | D10: =SUM(Freelancers!$E$5:$E$504) -> 1150 | F10: Abril | G10: =SUMIFS(Trabalhos!$G$5:$G$504,Trabalhos!$B$5:$B$504,">="&DATE($C$4,4,1),Trabalhos!$B$5:$B$504,"<"&DATE($C$4,4+1,1)) -> 0 | H10: =SUMIFS(Freelancers!$E$5:$E$504,Freelancers!$A$5:$A$504,">="&DATE($C$4,4,1),Freelancers!$A$5:$A$504,"<"&DATE($C$4,4+1,1)) -> 0 | I10: =SUMIFS(Gastos!$D$5:$D$504,Gastos!$A$5:$A$504,">="&DATE($C$4,4,1),Gastos!$A$5:$A$504,"<"&DATE($C$4,4+1,1)) -> 60 | J10: =G10-H10-I10 -> -60 | K10: =COUNTIFS(Trabalhos!$B$5:$B$504,">="&DATE($C$4,4,1),Trabalhos!$B$5:$B$504,"<"&DATE($C$4,4+1,1)) -> 0 | L10: =COUNTIFS(Orçamentos!$A$5:$A$504,">="&DATE($C$4,4,1),Orçamentos!$A$5:$A$504,"<"&DATE($C$4,4+1,1)) -> 0 | M10: =COUNTIFS(Orçamentos!$A$5:$A$504,">="&DATE($C$4,4,1),Orçamentos!$A$5:$A$504,"<"&DATE($C$4,4+1,1),Orçamentos!$F$5:$F$504,"Fechado") -> 0
B11: Outros gastos | C11: =SUMIFS(Gastos!$D$5:$D$504,Gastos!$A$5:$A$504,">="&DATE($C$4,1,1),Gastos!$A$5:$A$504,"<"&DATE($C$4+1,1,1)) -> 330 | D11: =SUM(Gastos!$D$5:$D$504) -> 330 | F11: Maio | G11: =SUMIFS(Trabalhos!$G$5:$G$504,Trabalhos!$B$5:$B$504,">="&DATE($C$4,5,1),Trabalhos!$B$5:$B$504,"<"&DATE($C$4,5+1,1)) -> 0 | H11: =SUMIFS(Freelancers!$E$5:$E$504,Freelancers!$A$5:$A$504,">="&DATE($C$4,5,1),Freelancers!$A$5:$A$504,"<"&DATE($C$4,5+1,1)) -> 0 | I11: =SUMIFS(Gastos!$D$5:$D$504,Gastos!$A$5:$A$504,">="&DATE($C$4,5,1),Gastos!$A$5:$A$504,"<"&DATE($C$4,5+1,1)) -> 0 | J11: =G11-H11-I11 -> 0 | K11: =COUNTIFS(Trabalhos!$B$5:$B$504,">="&DATE($C$4,5,1),Trabalhos!$B$5:$B$504,"<"&DATE($C$4,5+1,1)) -> 0 | L11: =COUNTIFS(Orçamentos!$A$5:$A$504,">="&DATE($C$4,5,1),Orçamentos!$A$5:$A$504,"<"&DATE($C$4,5+1,1)) -> 1 | M11: =COUNTIFS(Orçamentos!$A$5:$A$504,">="&DATE($C$4,5,1),Orçamentos!$A$5:$A$504,"<"&DATE($C$4,5+1,1),Orçamentos!$F$5:$F$504,"Fechado") -> 1
B12: LUCRO (bruto − freelas − gastos) | C12: =C7-C10-C11 -> 10120 | D12: =D7-D10-D11 -> 10120 | F12: Junho | G12: =SUMIFS(Trabalhos!$G$5:$G$504,Trabalhos!$B$5:$B$504,">="&DATE($C$4,6,1),Trabalhos!$B$5:$B$504,"<"&DATE($C$4,6+1,1)) -> 1800 | H12: =SUMIFS(Freelancers!$E$5:$E$504,Freelancers!$A$5:$A$504,">="&DATE($C$4,6,1),Freelancers!$A$5:$A$504,"<"&DATE($C$4,6+1,1)) -> 250 | I12: =SUMIFS(Gastos!$D$5:$D$504,Gastos!$A$5:$A$504,">="&DATE($C$4,6,1),Gastos!$A$5:$A$504,"<"&DATE($C$4,6+1,1)) -> 0 | J12: =G12-H12-I12 -> 1550 | K12: =COUNTIFS(Trabalhos!$B$5:$B$504,">="&DATE($C$4,6,1),Trabalhos!$B$5:$B$504,"<"&DATE($C$4,6+1,1)) -> 1 | L12: =COUNTIFS(Orçamentos!$A$5:$A$504,">="&DATE($C$4,6,1),Orçamentos!$A$5:$A$504,"<"&DATE($C$4,6+1,1)) -> 1 | M12: =COUNTIFS(Orçamentos!$A$5:$A$504,">="&DATE($C$4,6,1),Orçamentos!$A$5:$A$504,"<"&DATE($C$4,6+1,1),Orçamentos!$F$5:$F$504,"Fechado") -> 1
B13: Margem de lucro | C13: =IF(C7=0,0,C12/C7) -> 0.87241379 | D13: =IF(D7=0,0,D12/D7) -> 0.87241379 | F13: Julho | G13: =SUMIFS(Trabalhos!$G$5:$G$504,Trabalhos!$B$5:$B$504,">="&DATE($C$4,7,1),Trabalhos!$B$5:$B$504,"<"&DATE($C$4,7+1,1)) -> 0 | H13: =SUMIFS(Freelancers!$E$5:$E$504,Freelancers!$A$5:$A$504,">="&DATE($C$4,7,1),Freelancers!$A$5:$A$504,"<"&DATE($C$4,7+1,1)) -> 0 | I13: =SUMIFS(Gastos!$D$5:$D$504,Gastos!$A$5:$A$504,">="&DATE($C$4,7,1),Gastos!$A$5:$A$504,"<"&DATE($C$4,7+1,1)) -> 150 | J13: =G13-H13-I13 -> -150 | K13: =COUNTIFS(Trabalhos!$B$5:$B$504,">="&DATE($C$4,7,1),Trabalhos!$B$5:$B$504,"<"&DATE($C$4,7+1,1)) -> 0 | L13: =COUNTIFS(Orçamentos!$A$5:$A$504,">="&DATE($C$4,7,1),Orçamentos!$A$5:$A$504,"<"&DATE($C$4,7+1,1)) -> 1 | M13: =COUNTIFS(Orçamentos!$A$5:$A$504,">="&DATE($C$4,7,1),Orçamentos!$A$5:$A$504,"<"&DATE($C$4,7+1,1),Orçamentos!$F$5:$F$504,"Fechado") -> 0
B14: Trabalhos fechados | C14: =COUNTIFS(Trabalhos!$B$5:$B$504,">="&DATE($C$4,1,1),Trabalhos!$B$5:$B$504,"<"&DATE($C$4+1,1,1)) -> 5 | D14: =COUNT(Trabalhos!$B$5:$B$504) -> 5 | F14: Agosto | G14: =SUMIFS(Trabalhos!$G$5:$G$504,Trabalhos!$B$5:$B$504,">="&DATE($C$4,8,1),Trabalhos!$B$5:$B$504,"<"&DATE($C$4,8+1,1)) -> 900 | H14: =SUMIFS(Freelancers!$E$5:$E$504,Freelancers!$A$5:$A$504,">="&DATE($C$4,8,1),Freelancers!$A$5:$A$504,"<"&DATE($C$4,8+1,1)) -> 0 | I14: =SUMIFS(Gastos!$D$5:$D$504,Gastos!$A$5:$A$504,">="&DATE($C$4,8,1),Gastos!$A$5:$A$504,"<"&DATE($C$4,8+1,1)) -> 40 | J14: =G14-H14-I14 -> 860 | K14: =COUNTIFS(Trabalhos!$B$5:$B$504,">="&DATE($C$4,8,1),Trabalhos!$B$5:$B$504,"<"&DATE($C$4,8+1,1)) -> 1 | L14: =COUNTIFS(Orçamentos!$A$5:$A$504,">="&DATE($C$4,8,1),Orçamentos!$A$5:$A$504,"<"&DATE($C$4,8+1,1)) -> 1 | M14: =COUNTIFS(Orçamentos!$A$5:$A$504,">="&DATE($C$4,8,1),Orçamentos!$A$5:$A$504,"<"&DATE($C$4,8+1,1),Orçamentos!$F$5:$F$504,"Fechado") -> 1
B15: Valor médio por trabalho | C15: =IF(C14=0,0,C7/C14) -> 2320 | D15: =IF(D14=0,0,D7/D14) -> 2320 | F15: Setembro | G15: =SUMIFS(Trabalhos!$G$5:$G$504,Trabalhos!$B$5:$B$504,">="&DATE($C$4,9,1),Trabalhos!$B$5:$B$504,"<"&DATE($C$4,9+1,1)) -> 0 | H15: =SUMIFS(Freelancers!$E$5:$E$504,Freelancers!$A$5:$A$504,">="&DATE($C$4,9,1),Freelancers!$A$5:$A$504,"<"&DATE($C$4,9+1,1)) -> 0 | I15: =SUMIFS(Gastos!$D$5:$D$504,Gastos!$A$5:$A$504,">="&DATE($C$4,9,1),Gastos!$A$5:$A$504,"<"&DATE($C$4,9+1,1)) -> 0 | J15: =G15-H15-I15 -> 0 | K15: =COUNTIFS(Trabalhos!$B$5:$B$504,">="&DATE($C$4,9,1),Trabalhos!$B$5:$B$504,"<"&DATE($C$4,9+1,1)) -> 0 | L15: =COUNTIFS(Orçamentos!$A$5:$A$504,">="&DATE($C$4,9,1),Orçamentos!$A$5:$A$504,"<"&DATE($C$4,9+1,1)) -> 1 | M15: =COUNTIFS(Orçamentos!$A$5:$A$504,">="&DATE($C$4,9,1),Orçamentos!$A$5:$A$504,"<"&DATE($C$4,9+1,1),Orçamentos!$F$5:$F$504,"Fechado") -> 1
B16: Orçamentos passados | C16: =COUNTIFS(Orçamentos!$A$5:$A$504,">="&DATE($C$4,1,1),Orçamentos!$A$5:$A$504,"<"&DATE($C$4+1,1,1)) -> 8 | D16: =COUNT(Orçamentos!$A$5:$A$504) -> 8 | F16: Outubro | G16: =SUMIFS(Trabalhos!$G$5:$G$504,Trabalhos!$B$5:$B$504,">="&DATE($C$4,10,1),Trabalhos!$B$5:$B$504,"<"&DATE($C$4,10+1,1)) -> 0 | H16: =SUMIFS(Freelancers!$E$5:$E$504,Freelancers!$A$5:$A$504,">="&DATE($C$4,10,1),Freelancers!$A$5:$A$504,"<"&DATE($C$4,10+1,1)) -> 0 | I16: =SUMIFS(Gastos!$D$5:$D$504,Gastos!$A$5:$A$504,">="&DATE($C$4,10,1),Gastos!$A$5:$A$504,"<"&DATE($C$4,10+1,1)) -> 0 | J16: =G16-H16-I16 -> 0 | K16: =COUNTIFS(Trabalhos!$B$5:$B$504,">="&DATE($C$4,10,1),Trabalhos!$B$5:$B$504,"<"&DATE($C$4,10+1,1)) -> 0 | L16: =COUNTIFS(Orçamentos!$A$5:$A$504,">="&DATE($C$4,10,1),Orçamentos!$A$5:$A$504,"<"&DATE($C$4,10+1,1)) -> 1 | M16: =COUNTIFS(Orçamentos!$A$5:$A$504,">="&DATE($C$4,10,1),Orçamentos!$A$5:$A$504,"<"&DATE($C$4,10+1,1),Orçamentos!$F$5:$F$504,"Fechado") -> 0
B17: Orçamentos fechados | C17: =COUNTIFS(Orçamentos!$A$5:$A$504,">="&DATE($C$4,1,1),Orçamentos!$A$5:$A$504,"<"&DATE($C$4+1,1,1),Orçamentos!$F$5:$F$504,"Fechado") -> 5 | D17: =COUNTIF(Orçamentos!$F$5:$F$504,"Fechado") -> 5 | F17: Novembro | G17: =SUMIFS(Trabalhos!$G$5:$G$504,Trabalhos!$B$5:$B$504,">="&DATE($C$4,11,1),Trabalhos!$B$5:$B$504,"<"&DATE($C$4,11+1,1)) -> 1200 | H17: =SUMIFS(Freelancers!$E$5:$E$504,Freelancers!$A$5:$A$504,">="&DATE($C$4,11,1),Freelancers!$A$5:$A$504,"<"&DATE($C$4,11+1,1)) -> 0 | I17: =SUMIFS(Gastos!$D$5:$D$504,Gastos!$A$5:$A$504,">="&DATE($C$4,11,1),Gastos!$A$5:$A$504,"<"&DATE($C$4,11+1,1)) -> 0 | J17: =G17-H17-I17 -> 1200 | K17: =COUNTIFS(Trabalhos!$B$5:$B$504,">="&DATE($C$4,11,1),Trabalhos!$B$5:$B$504,"<"&DATE($C$4,11+1,1)) -> 1 | L17: =COUNTIFS(Orçamentos!$A$5:$A$504,">="&DATE($C$4,11,1),Orçamentos!$A$5:$A$504,"<"&DATE($C$4,11+1,1)) -> 0 | M17: =COUNTIFS(Orçamentos!$A$5:$A$504,">="&DATE($C$4,11,1),Orçamentos!$A$5:$A$504,"<"&DATE($C$4,11+1,1),Orçamentos!$F$5:$F$504,"Fechado") -> 0
B18: Taxa de fechamento | C18: =IF(C16=0,0,C17/C16) -> 0.625 | D18: =IF(D16=0,0,D17/D16) -> 0.625 | F18: Dezembro | G18: =SUMIFS(Trabalhos!$G$5:$G$504,Trabalhos!$B$5:$B$504,">="&DATE($C$4,12,1),Trabalhos!$B$5:$B$504,"<"&DATE($C$4,12+1,1)) -> 4200 | H18: =SUMIFS(Freelancers!$E$5:$E$504,Freelancers!$A$5:$A$504,">="&DATE($C$4,12,1),Freelancers!$A$5:$A$504,"<"&DATE($C$4,12+1,1)) -> 250 | I18: =SUMIFS(Gastos!$D$5:$D$504,Gastos!$A$5:$A$504,">="&DATE($C$4,12,1),Gastos!$A$5:$A$504,"<"&DATE($C$4,12+1,1)) -> 0 | J18: =G18-H18-I18 -> 3950 | K18: =COUNTIFS(Trabalhos!$B$5:$B$504,">="&DATE($C$4,12,1),Trabalhos!$B$5:$B$504,"<"&DATE($C$4,12+1,1)) -> 1 | L18: =COUNTIFS(Orçamentos!$A$5:$A$504,">="&DATE($C$4,12,1),Orçamentos!$A$5:$A$504,"<"&DATE($C$4,12+1,1)) -> 0 | M18: =COUNTIFS(Orçamentos!$A$5:$A$504,">="&DATE($C$4,12,1),Orçamentos!$A$5:$A$504,"<"&DATE($C$4,12+1,1),Orçamentos!$F$5:$F$504,"Fechado") -> 0
B19: Orçamentos aguardando resposta | C19: =COUNTIFS(Orçamentos!$A$5:$A$504,">="&DATE($C$4,1,1),Orçamentos!$A$5:$A$504,"<"&DATE($C$4+1,1,1),Orçamentos!$F$5:$F$504,"Aguardando") -> 1 | D19: =COUNTIF(Orçamentos!$F$5:$F$504,"Aguardando") -> 1 | F19: TOTAL | G19: =SUM(G7:G18) -> 11600 | H19: =SUM(H7:H18) -> 1150 | I19: =SUM(I7:I18) -> 330 | J19: =SUM(J7:J18) -> 10120 | K19: =SUM(K7:K18) -> 5 | L19: =SUM(L7:L18) -> 8 | M19: =SUM(M7:M18) -> 5
B20: Investido em equipamentos | C20: =SUMIFS(Equipamentos!$D$5:$D$504,Equipamentos!$C$5:$C$504,">="&DATE($C$4,1,1),Equipamentos!$C$5:$C$504,"<"&DATE($C$4+1,1,1)) -> 1000 | D20: =SUM(Equipamentos!$D$5:$D$504) -> 8900
B21: Equipamentos já pagos pelo lucro | C21: — | D21: =IF(D20=0,0,MAX(0,D12)/D20) -> 1.1370787
B22: Clientes cadastrados | C22: — | D22: =COUNTA(Clientes!$A$5:$A$504) -> 5
B24: "Equipamentos já pagos pelo lucro" = quanto do valor investido em equipamentos o seu lucro total já cobriu (100% = já se pagaram).
B26: Resultado por tipo de evento (ano escolhido)
B27: Tipo de evento | C27: Trabalhos | D27: Ganho bruto | F27: Freelancers | G27: Lucro | H27: Valor médio | I27: Orçam. passados | J27: Taxa fecham.
B28: =Listas!$A$5 -> Casamento | C28: =COUNTIFS(Trabalhos!$B$5:$B$504,">="&DATE($C$4,1,1),Trabalhos!$B$5:$B$504,"<"&DATE($C$4+1,1,1),Trabalhos!$E$5:$E$504,$B28) -> 2 | D28: =SUMIFS(Trabalhos!$G$5:$G$504,Trabalhos!$B$5:$B$504,">="&DATE($C$4,1,1),Trabalhos!$B$5:$B$504,"<"&DATE($C$4+1,1,1),Trabalhos!$E$5:$E$504,$B28) -> 7700 | F28: =SUMIFS(Trabalhos!$J$5:$J$504,Trabalhos!$B$5:$B$504,">="&DATE($C$4,1,1),Trabalhos!$B$5:$B$504,"<"&DATE($C$4+1,1,1),Trabalhos!$E$5:$E$504,$B28) -> 900 | G28: =SUMIFS(Trabalhos!$L$5:$L$504,Trabalhos!$B$5:$B$504,">="&DATE($C$4,1,1),Trabalhos!$B$5:$B$504,"<"&DATE($C$4+1,1,1),Trabalhos!$E$5:$E$504,$B28) -> 6720 | H28: =IF(C28=0,0,D28/C28) -> 3850 | I28: =COUNTIFS(Orçamentos!$A$5:$A$504,">="&DATE($C$4,1,1),Orçamentos!$A$5:$A$504,"<"&DATE($C$4+1,1,1),Orçamentos!$C$5:$C$504,$B28) -> 3 | J28: =IF(I28=0,0,COUNTIFS(Orçamentos!$A$5:$A$504,">="&DATE($C$4,1,1),Orçamentos!$A$5:$A$504,"<"&DATE($C$4+1,1,1),Orçamentos!$C$5:$C$504,$B28,Orçamentos!$F$5:$F$504,"Fechado")/I28) -> 0.66666667
B29: =Listas!$A$6 -> Empresa | C29: =COUNTIFS(Trabalhos!$B$5:$B$504,">="&DATE($C$4,1,1),Trabalhos!$B$5:$B$504,"<"&DATE($C$4+1,1,1),Trabalhos!$E$5:$E$504,$B29) -> 1 | D29: =SUMIFS(Trabalhos!$G$5:$G$504,Trabalhos!$B$5:$B$504,">="&DATE($C$4,1,1),Trabalhos!$B$5:$B$504,"<"&DATE($C$4+1,1,1),Trabalhos!$E$5:$E$504,$B29) -> 1800 | F29: =SUMIFS(Trabalhos!$J$5:$J$504,Trabalhos!$B$5:$B$504,">="&DATE($C$4,1,1),Trabalhos!$B$5:$B$504,"<"&DATE($C$4+1,1,1),Trabalhos!$E$5:$E$504,$B29) -> 250 | G29: =SUMIFS(Trabalhos!$L$5:$L$504,Trabalhos!$B$5:$B$504,">="&DATE($C$4,1,1),Trabalhos!$B$5:$B$504,"<"&DATE($C$4+1,1,1),Trabalhos!$E$5:$E$504,$B29) -> 1550 | H29: =IF(C29=0,0,D29/C29) -> 1800 | I29: =COUNTIFS(Orçamentos!$A$5:$A$504,">="&DATE($C$4,1,1),Orçamentos!$A$5:$A$504,"<"&DATE($C$4+1,1,1),Orçamentos!$C$5:$C$504,$B29) -> 1 | J29: =IF(I29=0,0,COUNTIFS(Orçamentos!$A$5:$A$504,">="&DATE($C$4,1,1),Orçamentos!$A$5:$A$504,"<"&DATE($C$4+1,1,1),Orçamentos!$C$5:$C$504,$B29,Orçamentos!$F$5:$F$504,"Fechado")/I29) -> 1
B30: =Listas!$A$7 -> Aniversário | C30: =COUNTIFS(Trabalhos!$B$5:$B$504,">="&DATE($C$4,1,1),Trabalhos!$B$5:$B$504,"<"&DATE($C$4+1,1,1),Trabalhos!$E$5:$E$504,$B30) -> 1 | D30: =SUMIFS(Trabalhos!$G$5:$G$504,Trabalhos!$B$5:$B$504,">="&DATE($C$4,1,1),Trabalhos!$B$5:$B$504,"<"&DATE($C$4+1,1,1),Trabalhos!$E$5:$E$504,$B30) -> 1200 | F30: =SUMIFS(Trabalhos!$J$5:$J$504,Trabalhos!$B$5:$B$504,">="&DATE($C$4,1,1),Trabalhos!$B$5:$B$504,"<"&DATE($C$4+1,1,1),Trabalhos!$E$5:$E$504,$B30) -> 0 | G30: =SUMIFS(Trabalhos!$L$5:$L$504,Trabalhos!$B$5:$B$504,">="&DATE($C$4,1,1),Trabalhos!$B$5:$B$504,"<"&DATE($C$4+1,1,1),Trabalhos!$E$5:$E$504,$B30) -> 1200 | H30: =IF(C30=0,0,D30/C30) -> 1200 | I30: =COUNTIFS(Orçamentos!$A$5:$A$504,">="&DATE($C$4,1,1),Orçamentos!$A$5:$A$504,"<"&DATE($C$4+1,1,1),Orçamentos!$C$5:$C$504,$B30) -> 2 | J30: =IF(I30=0,0,COUNTIFS(Orçamentos!$A$5:$A$504,">="&DATE($C$4,1,1),Orçamentos!$A$5:$A$504,"<"&DATE($C$4+1,1,1),Orçamentos!$C$5:$C$504,$B30,Orçamentos!$F$5:$F$504,"Fechado")/I30) -> 0.5
B31: =Listas!$A$8 -> Chá revelação | C31: =COUNTIFS(Trabalhos!$B$5:$B$504,">="&DATE($C$4,1,1),Trabalhos!$B$5:$B$504,"<"&DATE($C$4+1,1,1),Trabalhos!$E$5:$E$504,$B31) -> 1 | D31: =SUMIFS(Trabalhos!$G$5:$G$504,Trabalhos!$B$5:$B$504,">="&DATE($C$4,1,1),Trabalhos!$B$5:$B$504,"<"&DATE($C$4+1,1,1),Trabalhos!$E$5:$E$504,$B31) -> 900 | F31: =SUMIFS(Trabalhos!$J$5:$J$504,Trabalhos!$B$5:$B$504,">="&DATE($C$4,1,1),Trabalhos!$B$5:$B$504,"<"&DATE($C$4+1,1,1),Trabalhos!$E$5:$E$504,$B31) -> 0 | G31: =SUMIFS(Trabalhos!$L$5:$L$504,Trabalhos!$B$5:$B$504,">="&DATE($C$4,1,1),Trabalhos!$B$5:$B$504,"<"&DATE($C$4+1,1,1),Trabalhos!$E$5:$E$504,$B31) -> 860 | H31: =IF(C31=0,0,D31/C31) -> 900 | I31: =COUNTIFS(Orçamentos!$A$5:$A$504,">="&DATE($C$4,1,1),Orçamentos!$A$5:$A$504,"<"&DATE($C$4+1,1,1),Orçamentos!$C$5:$C$504,$B31) -> 2 | J31: =IF(I31=0,0,COUNTIFS(Orçamentos!$A$5:$A$504,">="&DATE($C$4,1,1),Orçamentos!$A$5:$A$504,"<"&DATE($C$4+1,1,1),Orçamentos!$C$5:$C$504,$B31,Orçamentos!$F$5:$F$504,"Fechado")/I31) -> 0.5
B32: =Listas!$A$9 -> Outro | C32: =COUNTIFS(Trabalhos!$B$5:$B$504,">="&DATE($C$4,1,1),Trabalhos!$B$5:$B$504,"<"&DATE($C$4+1,1,1),Trabalhos!$E$5:$E$504,$B32) -> 0 | D32: =SUMIFS(Trabalhos!$G$5:$G$504,Trabalhos!$B$5:$B$504,">="&DATE($C$4,1,1),Trabalhos!$B$5:$B$504,"<"&DATE($C$4+1,1,1),Trabalhos!$E$5:$E$504,$B32) -> 0 | F32: =SUMIFS(Trabalhos!$J$5:$J$504,Trabalhos!$B$5:$B$504,">="&DATE($C$4,1,1),Trabalhos!$B$5:$B$504,"<"&DATE($C$4+1,1,1),Trabalhos!$E$5:$E$504,$B32) -> 0 | G32: =SUMIFS(Trabalhos!$L$5:$L$504,Trabalhos!$B$5:$B$504,">="&DATE($C$4,1,1),Trabalhos!$B$5:$B$504,"<"&DATE($C$4+1,1,1),Trabalhos!$E$5:$E$504,$B32) -> 0 | H32: =IF(C32=0,0,D32/C32) -> 0 | I32: =COUNTIFS(Orçamentos!$A$5:$A$504,">="&DATE($C$4,1,1),Orçamentos!$A$5:$A$504,"<"&DATE($C$4+1,1,1),Orçamentos!$C$5:$C$504,$B32) -> 0 | J32: =IF(I32=0,0,COUNTIFS(Orçamentos!$A$5:$A$504,">="&DATE($C$4,1,1),Orçamentos!$A$5:$A$504,"<"&DATE($C$4+1,1,1),Orçamentos!$C$5:$C$504,$B32,Orçamentos!$F$5:$F$504,"Fechado")/I32) -> 0
B33: Lucro por tipo = valor cobrado − freelancers − gastos ligados ao trabalho (pelo código).
B35: De onde vêm seus clientes
B36: Como conheceu | C36: Clientes | D36: Total cobrado
B37: =Listas!$F$5 -> Instagram | C37: =COUNTIF(Clientes!$E$5:$E$504,$B37) -> 2 | D37: =SUMIFS(Clientes!$G$5:$G$504,Clientes!$E$5:$E$504,$B37) -> 4400
B38: =Listas!$F$6 -> Indicação | C38: =COUNTIF(Clientes!$E$5:$E$504,$B38) -> 2 | D38: =SUMIFS(Clientes!$G$5:$G$504,Clientes!$E$5:$E$504,$B38) -> 6000
B39: =Listas!$F$7 -> Site | C39: =COUNTIF(Clientes!$E$5:$E$504,$B39) -> 1 | D39: =SUMIFS(Clientes!$G$5:$G$504,Clientes!$E$5:$E$504,$B39) -> 1200
B40: =Listas!$F$8 -> Google | C40: =COUNTIF(Clientes!$E$5:$E$504,$B40) -> 0 | D40: =SUMIFS(Clientes!$G$5:$G$504,Clientes!$E$5:$E$504,$B40) -> 0
B41: =Listas!$F$9 -> WhatsApp | C41: =COUNTIF(Clientes!$E$5:$E$504,$B41) -> 0 | D41: =SUMIFS(Clientes!$G$5:$G$504,Clientes!$E$5:$E$504,$B41) -> 0
B42: =Listas!$F$10 -> Evento | C42: =COUNTIF(Clientes!$E$5:$E$504,$B42) -> 0 | D42: =SUMIFS(Clientes!$G$5:$G$504,Clientes!$E$5:$E$504,$B42) -> 0
B43: =Listas!$F$11 -> Outro | C43: =COUNTIF(Clientes!$E$5:$E$504,$B43) -> 0 | D43: =SUMIFS(Clientes!$G$5:$G$504,Clientes!$E$5:$E$504,$B43) -> 0
B45: Gráficos (ano escolhido)

Sheet Agenda
A1: Agenda — próximos eventos
A2: Automática: puxa da aba Trabalhos todos os eventos de hoje em diante, em ordem de data.
A4: # | B4: Data | C4: Faltam (dias) | D4: Horário | E4: Cliente | F4: Tipo de evento | G4: Local / cidade | H4: Código | I4: A receber
A5: 1 | B5: =IFERROR(INDEX(Trabalhos!$B$5:$B$504,MATCH($A5,Trabalhos!$O$5:$O$504,0)),"") -> 46347 | C5: =IF(B5="","",B5-TODAY()) -> 39 | D5: =IFERROR(INDEX(Trabalhos!$C$5:$C$504,MATCH($A5,Trabalhos!$O$5:$O$504,0)),"") -> 0.83333333 | E5: =IFERROR(INDEX(Trabalhos!$D$5:$D$504,MATCH($A5,Trabalhos!$O$5:$O$504,0)),"") -> Cliente Exemplo 3 | F5: =IFERROR(INDEX(Trabalhos!$E$5:$E$504,MATCH($A5,Trabalhos!$O$5:$O$504,0)),"") -> Aniversário | G5: =IFERROR(INDEX(Trabalhos!$F$5:$F$504,MATCH($A5,Trabalhos!$O$5:$O$504,0)),"") -> Hortolândia | H5: =IFERROR(INDEX(Trabalhos!$A$5:$A$504,MATCH($A5,Trabalhos!$O$5:$O$504,0)),"") -> T004 | I5: =IFERROR(INDEX(Trabalhos!$I$5:$I$504,MATCH($A5,Trabalhos!$O$5:$O$504,0)),"") -> 600
A6: 2 | B6: =IFERROR(INDEX(Trabalhos!$B$5:$B$504,MATCH($A6,Trabalhos!$O$5:$O$504,0)),"") -> 46361 | C6: =IF(B6="","",B6-TODAY()) -> 53 | D6: =IFERROR(INDEX(Trabalhos!$C$5:$C$504,MATCH($A6,Trabalhos!$O$5:$O$504,0)),"") -> 0.70833333 | E6: =IFERROR(INDEX(Trabalhos!$D$5:$D$504,MATCH($A6,Trabalhos!$O$5:$O$504,0)),"") -> Cliente Exemplo 4 | F6: =IFERROR(INDEX(Trabalhos!$E$5:$E$504,MATCH($A6,Trabalhos!$O$5:$O$504,0)),"") -> Casamento | G6: =IFERROR(INDEX(Trabalhos!$F$5:$F$504,MATCH($A6,Trabalhos!$O$5:$O$504,0)),"") -> Indaiatuba | H6: =IFERROR(INDEX(Trabalhos!$A$5:$A$504,MATCH($A6,Trabalhos!$O$5:$O$504,0)),"") -> T005 | I6: =IFERROR(INDEX(Trabalhos!$I$5:$I$504,MATCH($A6,Trabalhos!$O$5:$O$504,0)),"") -> 2100
A7: 3 | B7: =IFERROR(INDEX(Trabalhos!$B$5:$B$504,MATCH($A7,Trabalhos!$O$5:$O$504,0)),"") | C7: =IF(B7="","",B7-TODAY()) | D7: =IFERROR(INDEX(Trabalhos!$C$5:$C$504,MATCH($A7,Trabalhos!$O$5:$O$504,0)),"") | E7: =IFERROR(INDEX(Trabalhos!$D$5:$D$504,MATCH($A7,Trabalhos!$O$5:$O$504,0)),"") | F7: =IFERROR(INDEX(Trabalhos!$E$5:$E$504,MATCH($A7,Trabalhos!$O$5:$O$504,0)),"") | G7: =IFERROR(INDEX(Trabalhos!$F$5:$F$504,MATCH($A7,Trabalhos!$O$5:$O$504,0)),"") | H7: =IFERROR(INDEX(Trabalhos!$A$5:$A$504,MATCH($A7,Trabalhos!$O$5:$O$504,0)),"") | I7: =IFERROR(INDEX(Trabalhos!$I$5:$I$504,MATCH($A7,Trabalhos!$O$5:$O$504,0)),"")
A8: 4 | B8: =IFERROR(INDEX(Trabalhos!$B$5:$B$504,MATCH($A8,Trabalhos!$O$5:$O$504,0)),"") | C8: =IF(B8="","",B8-TODAY()) | D8: =IFERROR(INDEX(Trabalhos!$C$5:$C$504,MATCH($A8,Trabalhos!$O$5:$O$504,0)),"") | E8: =IFERROR(INDEX(Trabalhos!$D$5:$D$504,MATCH($A8,Trabalhos!$O$5:$O$504,0)),"") | F8: =IFERROR(INDEX(Trabalhos!$E$5:$E$504,MATCH($A8,Trabalhos!$O$5:$O$504,0)),"") | G8: =IFERROR(INDEX(Trabalhos!$F$5:$F$504,MATCH($A8,Trabalhos!$O$5:$O$504,0)),"") | H8: =IFERROR(INDEX(Trabalhos!$A$5:$A$504,MATCH($A8,Trabalhos!$O$5:$O$504,0)),"") | I8: =IFERROR(INDEX(Trabalhos!$I$5:$I$504,MATCH($A8,Trabalhos!$O$5:$O$504,0)),"")
A9: 5 | B9: =IFERROR(INDEX(Trabalhos!$B$5:$B$504,MATCH($A9,Trabalhos!$O$5:$O$504,0)),"") | C9: =IF(B9="","",B9-TODAY()) | D9: =IFERROR(INDEX(Trabalhos!$C$5:$C$504,MATCH($A9,Trabalhos!$O$5:$O$504,0)),"") | E9: =IFERROR(INDEX(Trabalhos!$D$5:$D$504,MATCH($A9,Trabalhos!$O$5:$O$504,0)),"") | F9: =IFERROR(INDEX(Trabalhos!$E$5:$E$504,MATCH($A9,Trabalhos!$O$5:$O$504,0)),"") | G9: =IFERROR(INDEX(Trabalhos!$F$5:$F$504,MATCH($A9,Trabalhos!$O$5:$O$504,0)),"") | H9: =IFERROR(INDEX(Trabalhos!$A$5:$A$504,MATCH($A9,Trabalhos!$O$5:$O$504,0)),"") | I9: =IFERROR(INDEX(Trabalhos!$I$5:$I$504,MATCH($A9,Trabalhos!$O$5:$O$504,0)),"")
A10: 6 | B10: =IFERROR(INDEX(Trabalhos!$B$5:$B$504,MATCH($A10,Trabalhos!$O$5:$O$504,0)),"") | C10: =IF(B10="","",B10-TODAY()) | D10: =IFERROR(INDEX(Trabalhos!$C$5:$C$504,MATCH($A10,Trabalhos!$O$5:$O$504,0)),"") | E10: =IFERROR(INDEX(Trabalhos!$D$5:$D$504,MATCH($A10,Trabalhos!$O$5:$O$504,0)),"") | F10: =IFERROR(INDEX(Trabalhos!$E$5:$E$504,MATCH($A10,Trabalhos!$O$5:$O$504,0)),"") | G10: =IFERROR(INDEX(Trabalhos!$F$5:$F$504,MATCH($A10,Trabalhos!$O$5:$O$504,0)),"") | H10: =IFERROR(INDEX(Trabalhos!$A$5:$A$504,MATCH($A10,Trabalhos!$O$5:$O$504,0)),"") | I10: =IFERROR(INDEX(Trabalhos!$I$5:$I$504,MATCH($A10,Trabalhos!$O$5:$O$504,0)),"")
A11: 7 | B11: =IFERROR(INDEX(Trabalhos!$B$5:$B$504,MATCH($A11,Trabalhos!$O$5:$O$504,0)),"") | C11: =IF(B11="","",B11-TODAY()) | D11: =IFERROR(INDEX(Trabalhos!$C$5:$C$504,MATCH($A11,Trabalhos!$O$5:$O$504,0)),"") | E11: =IFERROR(INDEX(Trabalhos!$D$5:$D$504,MATCH($A11,Trabalhos!$O$5:$O$504,0)),"") | F11: =IFERROR(INDEX(Trabalhos!$E$5:$E$504,MATCH($A11,Trabalhos!$O$5:$O$504,0)),"") | G11: =IFERROR(INDEX(Trabalhos!$F$5:$F$504,MATCH($A11,Trabalhos!$O$5:$O$504,0)),"") | H11: =IFERROR(INDEX(Trabalhos!$A$5:$A$504,MATCH($A11,Trabalhos!$O$5:$O$504,0)),"") | I11: =IFERROR(INDEX(Trabalhos!$I$5:$I$504,MATCH($A11,Trabalhos!$O$5:$O$504,0)),"")
A12: 8 | B12: =IFERROR(INDEX(Trabalhos!$B$5:$B$504,MATCH($A12,Trabalhos!$O$5:$O$504,0)),"") | C12: =IF(B12="","",B12-TODAY()) | D12: =IFERROR(INDEX(Trabalhos!$C$5:$C$504,MATCH($A12,Trabalhos!$O$5:$O$504,0)),"") | E12: =IFERROR(INDEX(Trabalhos!$D$5:$D$504,MATCH($A12,Trabalhos!$O$5:$O$504,0)),"") | F12: =IFERROR(INDEX(Trabalhos!$E$5:$E$504,MATCH($A12,Trabalhos!$O$5:$O$504,0)),"") | G12: =IFERROR(INDEX(Trabalhos!$F$5:$F$504,MATCH($A12,Trabalhos!$O$5:$O$504,0)),"") | H12: =IFERROR(INDEX(Trabalhos!$A$5:$A$504,MATCH($A12,Trabalhos!$O$5:$O$504,0)),"") | I12: =IFERROR(INDEX(Trabalhos!$I$5:$I$504,MATCH($A12,Trabalhos!$O$5:$O$504,0)),"")
A13: 9 | B13: =IFERROR(INDEX(Trabalhos!$B$5:$B$504,MATCH($A13,Trabalhos!$O$5:$O$504,0)),"") | C13: =IF(B13="","",B13-TODAY()) | D13: =IFERROR(INDEX(Trabalhos!$C$5:$C$504,MATCH($A13,Trabalhos!$O$5:$O$504,0)),"") | E13: =IFERROR(INDEX(Trabalhos!$D$5:$D$504,MATCH($A13,Trabalhos!$O$5:$O$504,0)),"") | F13: =IFERROR(INDEX(Trabalhos!$E$5:$E$504,MATCH($A13,Trabalhos!$O$5:$O$504,0)),"") | G13: =IFERROR(INDEX(Trabalhos!$F$5:$F$504,MATCH($A13,Trabalhos!$O$5:$O$504,0)),"") | H13: =IFERROR(INDEX(Trabalhos!$A$5:$A$504,MATCH($A13,Trabalhos!$O$5:$O$504,0)),"") | I13: =IFERROR(INDEX(Trabalhos!$I$5:$I$504,MATCH($A13,Trabalhos!$O$5:$O$504,0)),"")
A14: 10 | B14: =IFERROR(INDEX(Trabalhos!$B$5:$B$504,MATCH($A14,Trabalhos!$O$5:$O$504,0)),"") | C14: =IF(B14="","",B14-TODAY()) | D14: =IFERROR(INDEX(Trabalhos!$C$5:$C$504,MATCH($A14,Trabalhos!$O$5:$O$504,0)),"") | E14: =IFERROR(INDEX(Trabalhos!$D$5:$D$504,MATCH($A14,Trabalhos!$O$5:$O$504,0)),"") | F14: =IFERROR(INDEX(Trabalhos!$E$5:$E$504,MATCH($A14,Trabalhos!$O$5:$O$504,0)),"") | G14: =IFERROR(INDEX(Trabalhos!$F$5:$F$504,MATCH($A14,Trabalhos!$O$5:$O$504,0)),"") | H14: =IFERROR(INDEX(Trabalhos!$A$5:$A$504,MATCH($A14,Trabalhos!$O$5:$O$504,0)),"") | I14: =IFERROR(INDEX(Trabalhos!$I$5:$I$504,MATCH($A14,Trabalhos!$O$5:$O$504,0)),"")
A15: 11 | B15: =IFERROR(INDEX(Trabalhos!$B$5:$B$504,MATCH($A15,Trabalhos!$O$5:$O$504,0)),"") | C15: =IF(B15="","",B15-TODAY()) | D15: =IFERROR(INDEX(Trabalhos!$C$5:$C$504,MATCH($A15,Trabalhos!$O$5:$O$504,0)),"") | E15: =IFERROR(INDEX(Trabalhos!$D$5:$D$504,MATCH($A15,Trabalhos!$O$5:$O$504,0)),"") | F15: =IFERROR(INDEX(Trabalhos!$E$5:$E$504,MATCH($A15,Trabalhos!$O$5:$O$504,0)),"") | G15: =IFERROR(INDEX(Trabalhos!$F$5:$F$504,MATCH($A15,Trabalhos!$O$5:$O$504,0)),"") | H15: =IFERROR(INDEX(Trabalhos!$A$5:$A$504,MATCH($A15,Trabalhos!$O$5:$O$504,0)),"") | I15: =IFERROR(INDEX(Trabalhos!$I$5:$I$504,MATCH($A15,Trabalhos!$O$5:$O$504,0)),"")
A16: 12 | B16: =IFERROR(INDEX(Trabalhos!$B$5:$B$504,MATCH($A16,Trabalhos!$O$5:$O$504,0)),"") | C16: =IF(B16="","",B16-TODAY()) | D16: =IFERROR(INDEX(Trabalhos!$C$5:$C$504,MATCH($A16,Trabalhos!$O$5:$O$504,0)),"") | E16: =IFERROR(INDEX(Trabalhos!$D$5:$D$504,MATCH($A16,Trabalhos!$O$5:$O$504,0)),"") | F16: =IFERROR(INDEX(Trabalhos!$E$5:$E$504,MATCH($A16,Trabalhos!$O$5:$O$504,0)),"") | G16: =IFERROR(INDEX(Trabalhos!$F$5:$F$504,MATCH($A16,Trabalhos!$O$5:$O$504,0)),"") | H16: =IFERROR(INDEX(Trabalhos!$A$5:$A$504,MATCH($A16,Trabalhos!$O$5:$O$504,0)),"") | I16: =IFERROR(INDEX(Trabalhos!$I$5:$I$504,MATCH($A16,Trabalhos!$O$5:$O$504,0)),"")
... A44: 40 | B44: =IFERROR(INDEX(Trabalhos!$B$5:$B$504,MATCH($A44,Trabalhos!$O$5:$O$504,0)),"") | C44: =IF(B44="","",B44-TODAY()) | D44: =IFERROR(INDEX(Trabalhos!$C$5:$C$504,MATCH($A44,Trabalhos!$O$5:$O$504,0)),"") | E44: =IFERROR(INDEX(Trabalhos!$D$5:$D$504,MATCH($A44,Trabalhos!$O$5:$O$504,0)),"") | F44: =IFERROR(INDEX(Trabalhos!$E$5:$E$504,MATCH($A44,Trabalhos!$O$5:$O$504,0)),"") | G44: =IFERROR(INDEX(Trabalhos!$F$5:$F$504,MATCH($A44,Trabalhos!$O$5:$O$504,0)),"") | H44: =IFERROR(INDEX(Trabalhos!$A$5:$A$504,MATCH($A44,Trabalhos!$O$5:$O$504,0)),"") | I44: =IFERROR(INDEX(Trabalhos!$I$5:$I$504,MATCH($A44,Trabalhos!$O$5:$O$504,0)),"")
A46: Linhas em amarelo = evento nos próximos 7 dias.

Sheet Trabalhos
A1: Trabalhos fechados
A2: Um evento por linha. Colunas cinzas são automáticas. Use T001, T002, T003... no código.
A4: Código | B4: Data do evento | C4: Horário | D4: Cliente | E4: Tipo de evento | F4: Local / cidade | G4: Valor cobrado | H4: Valor recebido | I4: A receber | J4: Freelancers | K4: Outros gastos | L4: Lucro | M4: Pagamento | N4: Observações | O4: Ordem agenda
A5: T001 | B5: 46095 | C5: 0.66666667 | D5: Cliente Exemplo 1 | E5: Casamento | F5: Campinas | G5: 3500 | H5: 3500 | I5: =IF(G5="","",G5-H5) -> 0 | J5: =IF(A5="","",SUMIFS(Freelancers!$E$5:$E$504,Freelancers!$B$5:$B$504,A5)) -> 650 | K5: =IF(A5="","",SUMIFS(Gastos!$D$5:$D$504,Gastos!$E$5:$E$504,A5)) -> 80 | L5: =IF(G5="","",G5-N(J5)-N(K5)) -> 2770 | M5: =IF(G5="","",IF(H5>=G5,"Pago",IF(H5>0,"Parcial","Pendente"))) -> Pago | N5: EXEMPLO — apague esta linha | O5: =IF(OR(B5="",B5<TODAY()),"",COUNTIFS($B$5:$B$504,">="&TODAY(),$B$5:$B$504,"<"&B5)+COUNTIFS($B$5:B5,B5))
A6: T002 | B6: 46193 | C6: 0.79166667 | D6: Empresa Exemplo | E6: Empresa | F6: Valinhos | G6: 1800 | H6: 1800 | I6: =IF(G6="","",G6-H6) -> 0 | J6: =IF(A6="","",SUMIFS(Freelancers!$E$5:$E$504,Freelancers!$B$5:$B$504,A6)) -> 250 | K6: =IF(A6="","",SUMIFS(Gastos!$D$5:$D$504,Gastos!$E$5:$E$504,A6)) -> 0 | L6: =IF(G6="","",G6-N(J6)-N(K6)) -> 1550 | M6: =IF(G6="","",IF(H6>=G6,"Pago",IF(H6>0,"Parcial","Pendente"))) -> Pago | N6: EXEMPLO — apague esta linha | O6: =IF(OR(B6="",B6<TODAY()),"",COUNTIFS($B$5:$B$504,">="&TODAY(),$B$5:$B$504,"<"&B6)+COUNTIFS($B$5:B6,B6))
A7: T003 | B7: 46243 | C7: 0.625 | D7: Cliente Exemplo 2 | E7: Chá revelação | F7: Campinas | G7: 900 | H7: 900 | I7: =IF(G7="","",G7-H7) -> 0 | J7: =IF(A7="","",SUMIFS(Freelancers!$E$5:$E$504,Freelancers!$B$5:$B$504,A7)) -> 0 | K7: =IF(A7="","",SUMIFS(Gastos!$D$5:$D$504,Gastos!$E$5:$E$504,A7)) -> 40 | L7: =IF(G7="","",G7-N(J7)-N(K7)) -> 860 | M7: =IF(G7="","",IF(H7>=G7,"Pago",IF(H7>0,"Parcial","Pendente"))) -> Pago | N7: EXEMPLO — apague esta linha | O7: =IF(OR(B7="",B7<TODAY()),"",COUNTIFS($B$5:$B$504,">="&TODAY(),$B$5:$B$504,"<"&B7)+COUNTIFS($B$5:B7,B7))
A8: T004 | B8: 46347 | C8: 0.83333333 | D8: Cliente Exemplo 3 | E8: Aniversário | F8: Hortolândia | G8: 1200 | H8: 600 | I8: =IF(G8="","",G8-H8) -> 600 | J8: =IF(A8="","",SUMIFS(Freelancers!$E$5:$E$504,Freelancers!$B$5:$B$504,A8)) -> 0 | K8: =IF(A8="","",SUMIFS(Gastos!$D$5:$D$504,Gastos!$E$5:$E$504,A8)) -> 0 | L8: =IF(G8="","",G8-N(J8)-N(K8)) -> 1200 | M8: =IF(G8="","",IF(H8>=G8,"Pago",IF(H8>0,"Parcial","Pendente"))) -> Parcial | N8: EXEMPLO — apague esta linha | O8: =IF(OR(B8="",B8<TODAY()),"",COUNTIFS($B$5:$B$504,">="&TODAY(),$B$5:$B$504,"<"&B8)+COUNTIFS($B$5:B8,B8)) -> 1
A9: T005 | B9: 46361 | C9: 0.70833333 | D9: Cliente Exemplo 4 | E9: Casamento | F9: Indaiatuba | G9: 4200 | H9: 2100 | I9: =IF(G9="","",G9-H9) -> 2100 | J9: =IF(A9="","",SUMIFS(Freelancers!$E$5:$E$504,Freelancers!$B$5:$B$504,A9)) -> 250 | K9: =IF(A9="","",SUMIFS(Gastos!$D$5:$D$504,Gastos!$E$5:$E$504,A9)) -> 0 | L9: =IF(G9="","",G9-N(J9)-N(K9)) -> 3950 | M9: =IF(G9="","",IF(H9>=G9,"Pago",IF(H9>0,"Parcial","Pendente"))) -> Parcial | N9: EXEMPLO — apague esta linha | O9: =IF(OR(B9="",B9<TODAY()),"",COUNTIFS($B$5:$B$504,">="&TODAY(),$B$5:$B$504,"<"&B9)+COUNTIFS($B$5:B9,B9)) -> 2
I10: =IF(G10="","",G10-H10) | J10: =IF(A10="","",SUMIFS(Freelancers!$E$5:$E$504,Freelancers!$B$5:$B$504,A10)) | K10: =IF(A10="","",SUMIFS(Gastos!$D$5:$D$504,Gastos!$E$5:$E$504,A10)) | L10: =IF(G10="","",G10-N(J10)-N(K10)) | M10: =IF(G10="","",IF(H10>=G10,"Pago",IF(H10>0,"Parcial","Pendente"))) | O10: =IF(OR(B10="",B10<TODAY()),"",COUNTIFS($B$5:$B$504,">="&TODAY(),$B$5:$B$504,"<"&B10)+COUNTIFS($B$5:B10,B10))
I11: =IF(G11="","",G11-H11) | J11: =IF(A11="","",SUMIFS(Freelancers!$E$5:$E$504,Freelancers!$B$5:$B$504,A11)) | K11: =IF(A11="","",SUMIFS(Gastos!$D$5:$D$504,Gastos!$E$5:$E$504,A11)) | L11: =IF(G11="","",G11-N(J11)-N(K11)) | M11: =IF(G11="","",IF(H11>=G11,"Pago",IF(H11>0,"Parcial","Pendente"))) | O11: =IF(OR(B11="",B11<TODAY()),"",COUNTIFS($B$5:$B$504,">="&TODAY(),$B$5:$B$504,"<"&B11)+COUNTIFS($B$5:B11,B11))
I12: =IF(G12="","",G12-H12) | J12: =IF(A12="","",SUMIFS(Freelancers!$E$5:$E$504,Freelancers!$B$5:$B$504,A12)) | K12: =IF(A12="","",SUMIFS(Gastos!$D$5:$D$504,Gastos!$E$5:$E$504,A12)) | L12: =IF(G12="","",G12-N(J12)-N(K12)) | M12: =IF(G12="","",IF(H12>=G12,"Pago",IF(H12>0,"Parcial","Pendente"))) | O12: =IF(OR(B12="",B12<TODAY()),"",COUNTIFS($B$5:$B$504,">="&TODAY(),$B$5:$B$504,"<"&B12)+COUNTIFS($B$5:B12,B12))
I13: =IF(G13="","",G13-H13) | J13: =IF(A13="","",SUMIFS(Freelancers!$E$5:$E$504,Freelancers!$B$5:$B$504,A13)) | K13: =IF(A13="","",SUMIFS(Gastos!$D$5:$D$504,Gastos!$E$5:$E$504,A13)) | L13: =IF(G13="","",G13-N(J13)-N(K13)) | M13: =IF(G13="","",IF(H13>=G13,"Pago",IF(H13>0,"Parcial","Pendente"))) | O13: =IF(OR(B13="",B13<TODAY()),"",COUNTIFS($B$5:$B$504,">="&TODAY(),$B$5:$B$504,"<"&B13)+COUNTIFS($B$5:B13,B13))
I14: =IF(G14="","",G14-H14) | J14: =IF(A14="","",SUMIFS(Freelancers!$E$5:$E$504,Freelancers!$B$5:$B$504,A14)) | K14: =IF(A14="","",SUMIFS(Gastos!$D$5:$D$504,Gastos!$E$5:$E$504,A14)) | L14: =IF(G14="","",G14-N(J14)-N(K14)) | M14: =IF(G14="","",IF(H14>=G14,"Pago",IF(H14>0,"Parcial","Pendente"))) | O14: =IF(OR(B14="",B14<TODAY()),"",COUNTIFS($B$5:$B$504,">="&TODAY(),$B$5:$B$504,"<"&B14)+COUNTIFS($B$5:B14,B14))
I15: =IF(G15="","",G15-H15) | J15: =IF(A15="","",SUMIFS(Freelancers!$E$5:$E$504,Freelancers!$B$5:$B$504,A15)) | K15: =IF(A15="","",SUMIFS(Gastos!$D$5:$D$504,Gastos!$E$5:$E$504,A15)) | L15: =IF(G15="","",G15-N(J15)-N(K15)) | M15: =IF(G15="","",IF(H15>=G15,"Pago",IF(H15>0,"Parcial","Pendente"))) | O15: =IF(OR(B15="",B15<TODAY()),"",COUNTIFS($B$5:$B$504,">="&TODAY(),$B$5:$B$504,"<"&B15)+COUNTIFS($B$5:B15,B15))
I16: =IF(G16="","",G16-H16) | J16: =IF(A16="","",SUMIFS(Freelancers!$E$5:$E$504,Freelancers!$B$5:$B$504,A16)) | K16: =IF(A16="","",SUMIFS(Gastos!$D$5:$D$504,Gastos!$E$5:$E$504,A16)) | L16: =IF(G16="","",G16-N(J16)-N(K16)) | M16: =IF(G16="","",IF(H16>=G16,"Pago",IF(H16>0,"Parcial","Pendente"))) | O16: =IF(OR(B16="",B16<TODAY()),"",COUNTIFS($B$5:$B$504,">="&TODAY(),$B$5:$B$504,"<"&B16)+COUNTIFS($B$5:B16,B16))
I17: =IF(G17="","",G17-H17) | J17: =IF(A17="","",SUMIFS(Freelancers!$E$5:$E$504,Freelancers!$B$5:$B$504,A17)) | K17: =IF(A17="","",SUMIFS(Gastos!$D$5:$D$504,Gastos!$E$5:$E$504,A17)) | L17: =IF(G17="","",G17-N(J17)-N(K17)) | M17: =IF(G17="","",IF(H17>=G17,"Pago",IF(H17>0,"Parcial","Pendente"))) | O17: =IF(OR(B17="",B17<TODAY()),"",COUNTIFS($B$5:$B$504,">="&TODAY(),$B$5:$B$504,"<"&B17)+COUNTIFS($B$5:B17,B17))
I18: =IF(G18="","",G18-H18) | J18: =IF(A18="","",SUMIFS(Freelancers!$E$5:$E$504,Freelancers!$B$5:$B$504,A18)) | K18: =IF(A18="","",SUMIFS(Gastos!$D$5:$D$504,Gastos!$E$5:$E$504,A18)) | L18: =IF(G18="","",G18-N(J18)-N(K18)) | M18: =IF(G18="","",IF(H18>=G18,"Pago",IF(H18>0,"Parcial","Pendente"))) | O18: =IF(OR(B18="",B18<TODAY()),"",COUNTIFS($B$5:$B$504,">="&TODAY(),$B$5:$B$504,"<"&B18)+COUNTIFS($B$5:B18,B18))
I19: =IF(G19="","",G19-H19) | J19: =IF(A19="","",SUMIFS(Freelancers!$E$5:$E$504,Freelancers!$B$5:$B$504,A19)) | K19: =IF(A19="","",SUMIFS(Gastos!$D$5:$D$504,Gastos!$E$5:$E$504,A19)) | L19: =IF(G19="","",G19-N(J19)-N(K19)) | M19: =IF(G19="","",IF(H19>=G19,"Pago",IF(H19>0,"Parcial","Pendente"))) | O19: =IF(OR(B19="",B19<TODAY()),"",COUNTIFS($B$5:$B$504,">="&TODAY(),$B$5:$B$504,"<"&B19)+COUNTIFS($B$5:B19,B19))
I20: =IF(G20="","",G20-H20) | J20: =IF(A20="","",SUMIFS(Freelancers!$E$5:$E$504,Freelancers!$B$5:$B$504,A20)) | K20: =IF(A20="","",SUMIFS(Gastos!$D$5:$D$504,Gastos!$E$5:$E$504,A20)) | L20: =IF(G20="","",G20-N(J20)-N(K20)) | M20: =IF(G20="","",IF(H20>=G20,"Pago",IF(H20>0,"Parcial","Pendente"))) | O20: =IF(OR(B20="",B20<TODAY()),"",COUNTIFS($B$5:$B$504,">="&TODAY(),$B$5:$B$504,"<"&B20)+COUNTIFS($B$5:B20,B20))
I21: =IF(G21="","",G21-H21) | J21: =IF(A21="","",SUMIFS(Freelancers!$E$5:$E$504,Freelancers!$B$5:$B$504,A21)) | K21: =IF(A21="","",SUMIFS(Gastos!$D$5:$D$504,Gastos!$E$5:$E$504,A21)) | L21: =IF(G21="","",G21-N(J21)-N(K21)) | M21: =IF(G21="","",IF(H21>=G21,"Pago",IF(H21>0,"Parcial","Pendente"))) | O21: =IF(OR(B21="",B21<TODAY()),"",COUNTIFS($B$5:$B$504,">="&TODAY(),$B$5:$B$504,"<"&B21)+COUNTIFS($B$5:B21,B21))
... I504: =IF(G504="","",G504-H504) | J504: =IF(A504="","",SUMIFS(Freelancers!$E$5:$E$504,Freelancers!$B$5:$B$504,A504)) | K504: =IF(A504="","",SUMIFS(Gastos!$D$5:$D$504,Gastos!$E$5:$E$504,A504)) | L504: =IF(G504="","",G504-N(J504)-N(K504)) | M504: =IF(G504="","",IF(H504>=G504,"Pago",IF(H504>0,"Parcial","Pendente"))) | O504: =IF(OR(B504="",B504<TODAY()),"",COUNTIFS($B$5:$B$504,">="&TODAY(),$B$5:$B$504,"<"&B504)+COUNTIFS($B$5:B504,B504))

Sheet Orçamentos
A1: Orçamentos passados
A2: Anote TODOS os orçamentos, fechando ou não. É isso que mostra a sua taxa de fechamento.
A4: Data do envio | B4: Cliente | C4: Tipo de evento | D4: Data do evento | E4: Valor orçado | F4: Status | G4: Observações
A5: 46042 | B5: Cliente Exemplo 1 | C5: Casamento | D5: 46095 | E5: 3500 | F5: Fechado | G5: EXEMPLO — apague esta linha
A6: 46056 | B6: Cliente Exemplo 5 | C6: Casamento | D6: 46151 | E6: 3800 | F6: Recusado | G6: EXEMPLO — apague esta linha (achou caro)
A7: 46154 | B7: Empresa Exemplo | C7: Empresa | D7: 46193 | E7: 1800 | F7: Fechado | G7: EXEMPLO — apague esta linha
A8: 46201 | B8: Cliente Exemplo 2 | C8: Chá revelação | D8: 46243 | E8: 900 | F8: Fechado | G8: EXEMPLO — apague esta linha
A9: 46218 | B9: Cliente Exemplo 6 | C9: Aniversário | D9: 46277 | E9: 1100 | F9: Recusado | G9: EXEMPLO — apague esta linha (data ocupada)
A10: 46264 | B10: Cliente Exemplo 3 | C10: Aniversário | D10: 46347 | E10: 1200 | F10: Fechado | G10: EXEMPLO — apague esta linha
A11: 46275 | B11: Cliente Exemplo 4 | C11: Casamento | D11: 46361 | E11: 4200 | F11: Fechado | G11: EXEMPLO — apague esta linha
A12: 46297 | B12: Cliente Exemplo 7 | C12: Chá revelação | D12: 46403 | E12: 950 | F12: Aguardando | G12: EXEMPLO — apague esta linha

Sheet Clientes
A1: Clientes
A2: Um cliente por linha. Use o MESMO nome nas abas Trabalhos e Orçamentos.
A4: Nome | B4: WhatsApp | C4: Instagram | D4: Cidade | E4: Como conheceu | F4: Trabalhos | G4: Total já cobrado | H4: Observações
A5: Cliente Exemplo 1 | B5: (19) 90000-0001 | C5: @exemplo1 | D5: Campinas | E5: Instagram | F5: =IF(A5="","",COUNTIF(Trabalhos!$D$5:$D$504,A5)) -> 1 | G5: =IF(A5="","",SUMIFS(Trabalhos!$G$5:$G$504,Trabalhos!$D$5:$D$504,A5)) -> 3500 | H5: EXEMPLO — apague esta linha
A6: Empresa Exemplo | B6: (19) 90000-0002 | C6: @empresaexemplo | D6: Valinhos | E6: Indicação | F6: =IF(A6="","",COUNTIF(Trabalhos!$D$5:$D$504,A6)) -> 1 | G6: =IF(A6="","",SUMIFS(Trabalhos!$G$5:$G$504,Trabalhos!$D$5:$D$504,A6)) -> 1800 | H6: EXEMPLO — apague esta linha
A7: Cliente Exemplo 2 | B7: (19) 90000-0003 | C7: @exemplo2 | D7: Campinas | E7: Instagram | F7: =IF(A7="","",COUNTIF(Trabalhos!$D$5:$D$504,A7)) -> 1 | G7: =IF(A7="","",SUMIFS(Trabalhos!$G$5:$G$504,Trabalhos!$D$5:$D$504,A7)) -> 900 | H7: EXEMPLO — apague esta linha
A8: Cliente Exemplo 3 | B8: (19) 90000-0004 | C8: @exemplo3 | D8: Hortolândia | E8: Site | F8: =IF(A8="","",COUNTIF(Trabalhos!$D$5:$D$504,A8)) -> 1 | G8: =IF(A8="","",SUMIFS(Trabalhos!$G$5:$G$504,Trabalhos!$D$5:$D$504,A8)) -> 1200 | H8: EXEMPLO — apague esta linha
A9: Cliente Exemplo 4 | B9: (19) 90000-0005 | C9: @exemplo4 | D9: Indaiatuba | E9: Indicação | F9: =IF(A9="","",COUNTIF(Trabalhos!$D$5:$D$504,A9)) -> 1 | G9: =IF(A9="","",SUMIFS(Trabalhos!$G$5:$G$504,Trabalhos!$D$5:$D$504,A9)) -> 4200 | H9: EXEMPLO — apague esta linha
F10: =IF(A10="","",COUNTIF(Trabalhos!$D$5:$D$504,A10)) | G10: =IF(A10="","",SUMIFS(Trabalhos!$G$5:$G$504,Trabalhos!$D$5:$D$504,A10))
F11: =IF(A11="","",COUNTIF(Trabalhos!$D$5:$D$504,A11)) | G11: =IF(A11="","",SUMIFS(Trabalhos!$G$5:$G$504,Trabalhos!$D$5:$D$504,A11))
F12: =IF(A12="","",COUNTIF(Trabalhos!$D$5:$D$504,A12)) | G12: =IF(A12="","",SUMIFS(Trabalhos!$G$5:$G$504,Trabalhos!$D$5:$D$504,A12))
F13: =IF(A13="","",COUNTIF(Trabalhos!$D$5:$D$504,A13)) | G13: =IF(A13="","",SUMIFS(Trabalhos!$G$5:$G$504,Trabalhos!$D$5:$D$504,A13))
F14: =IF(A14="","",COUNTIF(Trabalhos!$D$5:$D$504,A14)) | G14: =IF(A14="","",SUMIFS(Trabalhos!$G$5:$G$504,Trabalhos!$D$5:$D$504,A14))
F15: =IF(A15="","",COUNTIF(Trabalhos!$D$5:$D$504,A15)) | G15: =IF(A15="","",SUMIFS(Trabalhos!$G$5:$G$504,Trabalhos!$D$5:$D$504,A15))
F16: =IF(A16="","",COUNTIF(Trabalhos!$D$5:$D$504,A16)) | G16: =IF(A16="","",SUMIFS(Trabalhos!$G$5:$G$504,Trabalhos!$D$5:$D$504,A16))
F17: =IF(A17="","",COUNTIF(Trabalhos!$D$5:$D$504,A17)) | G17: =IF(A17="","",SUMIFS(Trabalhos!$G$5:$G$504,Trabalhos!$D$5:$D$504,A17))
F18: =IF(A18="","",COUNTIF(Trabalhos!$D$5:$D$504,A18)) | G18: =IF(A18="","",SUMIFS(Trabalhos!$G$5:$G$504,Trabalhos!$D$5:$D$504,A18))
F19: =IF(A19="","",COUNTIF(Trabalhos!$D$5:$D$504,A19)) | G19: =IF(A19="","",SUMIFS(Trabalhos!$G$5:$G$504,Trabalhos!$D$5:$D$504,A19))
F20: =IF(A20="","",COUNTIF(Trabalhos!$D$5:$D$504,A20)) | G20: =IF(A20="","",SUMIFS(Trabalhos!$G$5:$G$504,Trabalhos!$D$5:$D$504,A20))
F21: =IF(A21="","",COUNTIF(Trabalhos!$D$5:$D$504,A21)) | G21: =IF(A21="","",SUMIFS(Trabalhos!$G$5:$G$504,Trabalhos!$D$5:$D$504,A21))
... F504: =IF(A504="","",COUNTIF(Trabalhos!$D$5:$D$504,A504)) | G504: =IF(A504="","",SUMIFS(Trabalhos!$G$5:$G$504,Trabalhos!$D$5:$D$504,A504))

Sheet Freelancers
A1: Pagamentos a freelancers
A2: Um pagamento por linha. O código do trabalho liga o gasto ao evento (T001, T002...).
A4: Data | B4: Código do trabalho | C4: Nome do freelancer | D4: Função | E4: Valor pago | F4: Já pago? | G4: Observações
A5: 46095 | B5: T001 | C5: Freela Exemplo A | D5: Fotógrafo | E5: 450 | F5: Sim | G5: EXEMPLO — apague esta linha
A6: 46095 | B6: T001 | C6: Freela Exemplo B | D6: Assistente | E6: 200 | F6: Sim | G6: EXEMPLO — apague esta linha
A7: 46193 | B7: T002 | C7: Freela Exemplo C | D7: Editor | E7: 250 | F7: Sim | G7: EXEMPLO — apague esta linha
A8: 46361 | B8: T005 | C8: Freela Exemplo B | D8: Assistente | E8: 250 | F8: Não | G8: EXEMPLO — apague esta linha

Sheet Gastos
A1: Outros gastos
A2: Despesas do negócio. Se for de um trabalho específico, coloque o código dele.
A4: Data | B4: Categoria | C4: Descrição | D4: Valor | E4: Código do trabalho (opcional) | F4: Observações
A5: 46095 | B5: Combustível / transporte | C5: Gasolina ida e volta | D5: 80 | E5: T001 | F5: EXEMPLO — apague esta linha
A6: 46113 | B6: Aplicativos / software | C6: Assinatura app de edição | D6: 60 | F6: EXEMPLO — apague esta linha
A7: 46213 | B7: Anúncios / marketing | C7: Impulsionamento Instagram | D7: 150 | F7: EXEMPLO — apague esta linha
A8: 46243 | B8: Alimentação | C8: Lanche no evento | D8: 40 | E8: T003 | F8: EXEMPLO — apague esta linha

Sheet Equipamentos
A1: Equipamentos (investimentos)
A2: Tudo o que você comprou para trabalhar.
A4: Equipamento | B4: Categoria | C4: Data da compra | D4: Valor pago | E4: Forma de pagamento | F4: Situação | G4: Observações
A5: Celular (exemplo) | B5: Celular | C5: 45971 | D5: 7000 | E5: Parcelado | F5: Em uso | G5: EXEMPLO — apague esta linha
A6: Gimbal (exemplo) | B6: Estabilizador / gimbal | C6: 45971 | D6: 900 | E6: Pix | F6: Em uso | G6: EXEMPLO — apague esta linha
A7: Microfone sem fio (exemplo) | B7: Áudio | C7: 46058 | D7: 650 | E7: Cartão de crédito | F7: Em uso | G7: EXEMPLO — apague esta linha
A8: Luz LED (exemplo) | B8: Iluminação | C8: 46160 | D8: 350 | E8: Pix | F8: Em uso | G8: EXEMPLO — apague esta linha

Sheet Listas
A1: Opções dos menus
A2: Pode adicionar novas opções nas linhas vazias de cada coluna. Evite renomear "Fechado", "Aguardando" e "Recusado".
A4: Tipos de evento | B4: Status do orçamento | C4: Função do freelancer | D4: Categorias de gasto | E4: Categorias de equipamento | F4: Como o cliente conheceu | G4: Situação do equipamento | H4: Sim / Não | I4: Forma de pagamento
A5: Casamento | B5: Aguardando | C5: Fotógrafo | D5: Combustível / transporte | E5: Câmera | F5: Instagram | G5: Em uso | H5: Sim | I5: Pix
A6: Empresa | B6: Fechado | C6: Videomaker | D6: Alimentação | E6: Celular | F6: Indicação | G6: Vendido | H6: Não | I6: Dinheiro
A7: Aniversário | B7: Recusado | C7: Storymaker | D7: Aplicativos / software | E7: Lente | F7: Site | G7: Quebrado / perdido | I7: Cartão de crédito
A8: Chá revelação | C8: Assistente | D8: Cursos | E8: Estabilizador / gimbal | F8: Google | I8: Cartão de débito
A9: Outro | C9: Editor | D9: Anúncios / marketing | E9: Áudio | F9: WhatsApp | I9: Parcelado
C10: Drone | D10: Manutenção | E10: Iluminação | F10: Evento | I10: Boleto
C11: Outro | D11: Acessórios | E11: Drone | F11: Outro
D12: Impostos / taxas | E12: Computador
D13: Outro | E13: Armazenamento
E14: Outro
