Workbook

Sheet Como usar
B2: Controle Financeiro — Darzan Produções
B3: João Darzan · Videomaker & Storymaker · Campinas e região
B5: NO DIA A DIA
B6: 1. Fechou um trabalho? | C6: Uma linha na aba Trabalhos: data, cliente, tipo de serviço, o que foi fechado, valor e quanto já recebeu. Pronto.
B7: 2. Passou um orçamento? | C7: Uma linha na aba Orçamentos, mesmo que o cliente ainda não tenha respondido. Quando ele responder, troque o Status para Fechado ou Recusado.
B8: 3. Cliente novo? | C8: Cadastre na aba Clientes (nome, WhatsApp, Instagram, como te conheceu). Use o mesmo nome nas outras abas.
B9: 4. Pagou um freela? | C9: Na própria linha do trabalho: quem foi (coluna Freelancers) e quanto custou (coluna Custo com freelancers).
B10: 5. Gasto do negócio? | C10: Combustível, aplicativo, anúncio, curso: aba Despesas. Equipamento novo: aba Equipamentos.
B12: REGRAS SIMPLES
B13: Colunas | C13: BRANCAS você preenche. CINZAS são automáticas, não digite nelas. Não renomeie os títulos das colunas: o painel encontra os dados por eles.
B14: O que foi fechado | C14: Escreva as entregas combinadas com o cliente: "Teaser + filme completo + 10 reels", "Storymaker 6h", "Ensaio 50 fotos". Isso aparece no painel em cada tipo de serviço.
B15: Datas e valores | C15: Datas como 14/03/2026. Valores só com números (2500 ou 2500,50); o R$ aparece sozinho.
B16: Lucro | C16: Lucro de cada trabalho = valor fechado − freelancers − outros custos do trabalho. No resumo do mês e do ano, as despesas gerais também são descontadas.
B17: Exemplos | C17: As linhas marcadas com EXEMPLO servem só para você ver tudo funcionando. Apague essas linhas antes de começar.
B19: PAINEL AUTOMÁTICO
B20: O que é | C20: Um painel no estilo da Darzan que lê esta planilha sozinho. Mexeu aqui, o painel já mostra. Só você acessa, com o seu login do Google.
B21: Como instalar | C21: Uma vez só: Extensões → Apps Script → cole os dois arquivos que o Claude te mandou → Implantar. O passo a passo completo está na conversa e no arquivo LEIA-ME.
B22: Como abrir | C22: Pelo menu Darzan → Abrir painel (aqui na planilha) ou pelo link do painel no celular.
B24: RESUMO
B25: Aba Resumo | C25: Mesmo sem o painel, a aba Resumo mostra o ano e o mês que você escolher (células amarelas), mês a mês e por tipo de serviço.

Sheet Resumo
B1: Resumo — Darzan Produções
B2: Tudo automático. Escolha o ano e o mês nas células amarelas.
B4: Ano: | C4: 2026
B5: Mês: | C5: Outubro
B7: Indicador | C7: No ano | D7: No mês escolhido | F7: Mês | G7: Faturamento | H7: Custos | I7: Lucro | J7: Trabalhos | K7: Orçamentos | L7: Fechados
B8: Faturamento (valor fechado) | C8: =SUMIFS(Trabalhos!$G$2:$G$1001,Trabalhos!$A$2:$A$1001,">="&DATE($C$4,1,1),Trabalhos!$A$2:$A$1001,"<"&DATE($C$4+1,1,1)) -> 41710 | D8: =SUMIFS(Trabalhos!$G$2:$G$1001,Trabalhos!$A$2:$A$1001,">="&DATE($C$4,IFERROR(MATCH($C$5,Listas!$H$3:$H$14,0),1),1),Trabalhos!$A$2:$A$1001,"<"&DATE($C$4,IFERROR(MATCH($C$5,Listas!$H$3:$H$14,0),12)+1,1)) -> 4100 | F8: Janeiro | G8: =SUMIFS(Trabalhos!$G$2:$G$1001,Trabalhos!$A$2:$A$1001,">="&DATE($C$4,1,1),Trabalhos!$A$2:$A$1001,"<"&DATE($C$4,1+1,1)) -> 4800 | H8: =SUMIFS(Trabalhos!$K$2:$K$1001,Trabalhos!$A$2:$A$1001,">="&DATE($C$4,1,1),Trabalhos!$A$2:$A$1001,"<"&DATE($C$4,1+1,1))+SUMIFS(Trabalhos!$L$2:$L$1001,Trabalhos!$A$2:$A$1001,">="&DATE($C$4,1,1),Trabalhos!$A$2:$A$1001,"<"&DATE($C$4,1+1,1))+SUMIFS(Despesas!$D$2:$D$1001,Despesas!$A$2:$A$1001,">="&DATE($C$4,1,1),Despesas!$A$2:$A$1001,"<"&DATE($C$4,1+1,1)) -> 680 | I8: =G8-H8 -> 4120 | J8: =COUNTIFS(Trabalhos!$A$2:$A$1001,">="&DATE($C$4,1,1),Trabalhos!$A$2:$A$1001,"<"&DATE($C$4,1+1,1)) -> 1 | K8: =COUNTIFS(Orçamentos!$A$2:$A$1001,">="&DATE($C$4,1,1),Orçamentos!$A$2:$A$1001,"<"&DATE($C$4,1+1,1)) -> 1 | L8: =COUNTIFS(Orçamentos!$A$2:$A$1001,">="&DATE($C$4,1,1),Orçamentos!$A$2:$A$1001,"<"&DATE($C$4,1+1,1),Orçamentos!$G$2:$G$1001,"Fechado") -> 1
B9: Já recebido | C9: =SUMIFS(Trabalhos!$H$2:$H$1001,Trabalhos!$A$2:$A$1001,">="&DATE($C$4,1,1),Trabalhos!$A$2:$A$1001,"<"&DATE($C$4+1,1,1)) -> 35460 | D9: =SUMIFS(Trabalhos!$H$2:$H$1001,Trabalhos!$A$2:$A$1001,">="&DATE($C$4,IFERROR(MATCH($C$5,Listas!$H$3:$H$14,0),1),1),Trabalhos!$A$2:$A$1001,"<"&DATE($C$4,IFERROR(MATCH($C$5,Listas!$H$3:$H$14,0),12)+1,1)) -> 2050 | F9: Fevereiro | G9: =SUMIFS(Trabalhos!$G$2:$G$1001,Trabalhos!$A$2:$A$1001,">="&DATE($C$4,2,1),Trabalhos!$A$2:$A$1001,"<"&DATE($C$4,2+1,1)) -> 1200 | H9: =SUMIFS(Trabalhos!$K$2:$K$1001,Trabalhos!$A$2:$A$1001,">="&DATE($C$4,2,1),Trabalhos!$A$2:$A$1001,"<"&DATE($C$4,2+1,1))+SUMIFS(Trabalhos!$L$2:$L$1001,Trabalhos!$A$2:$A$1001,">="&DATE($C$4,2,1),Trabalhos!$A$2:$A$1001,"<"&DATE($C$4,2+1,1))+SUMIFS(Despesas!$D$2:$D$1001,Despesas!$A$2:$A$1001,">="&DATE($C$4,2,1),Despesas!$A$2:$A$1001,"<"&DATE($C$4,2+1,1)) -> 100 | I9: =G9-H9 -> 1100 | J9: =COUNTIFS(Trabalhos!$A$2:$A$1001,">="&DATE($C$4,2,1),Trabalhos!$A$2:$A$1001,"<"&DATE($C$4,2+1,1)) -> 1 | K9: =COUNTIFS(Orçamentos!$A$2:$A$1001,">="&DATE($C$4,2,1),Orçamentos!$A$2:$A$1001,"<"&DATE($C$4,2+1,1)) -> 3 | L9: =COUNTIFS(Orçamentos!$A$2:$A$1001,">="&DATE($C$4,2,1),Orçamentos!$A$2:$A$1001,"<"&DATE($C$4,2+1,1),Orçamentos!$G$2:$G$1001,"Fechado") -> 2
B10: A receber | C10: =C8-C9 -> 6250 | D10: =D8-D9 -> 2050 | F10: Março | G10: =SUMIFS(Trabalhos!$G$2:$G$1001,Trabalhos!$A$2:$A$1001,">="&DATE($C$4,3,1),Trabalhos!$A$2:$A$1001,"<"&DATE($C$4,3+1,1)) -> 4400 | H10: =SUMIFS(Trabalhos!$K$2:$K$1001,Trabalhos!$A$2:$A$1001,">="&DATE($C$4,3,1),Trabalhos!$A$2:$A$1001,"<"&DATE($C$4,3+1,1))+SUMIFS(Trabalhos!$L$2:$L$1001,Trabalhos!$A$2:$A$1001,">="&DATE($C$4,3,1),Trabalhos!$A$2:$A$1001,"<"&DATE($C$4,3+1,1))+SUMIFS(Despesas!$D$2:$D$1001,Despesas!$A$2:$A$1001,">="&DATE($C$4,3,1),Despesas!$A$2:$A$1001,"<"&DATE($C$4,3+1,1)) -> 750 | I10: =G10-H10 -> 3650 | J10: =COUNTIFS(Trabalhos!$A$2:$A$1001,">="&DATE($C$4,3,1),Trabalhos!$A$2:$A$1001,"<"&DATE($C$4,3+1,1)) -> 2 | K10: =COUNTIFS(Orçamentos!$A$2:$A$1001,">="&DATE($C$4,3,1),Orçamentos!$A$2:$A$1001,"<"&DATE($C$4,3+1,1)) -> 1 | L10: =COUNTIFS(Orçamentos!$A$2:$A$1001,">="&DATE($C$4,3,1),Orçamentos!$A$2:$A$1001,"<"&DATE($C$4,3+1,1),Orçamentos!$G$2:$G$1001,"Fechado") -> 1
B11: Freelancers | C11: =SUMIFS(Trabalhos!$K$2:$K$1001,Trabalhos!$A$2:$A$1001,">="&DATE($C$4,1,1),Trabalhos!$A$2:$A$1001,"<"&DATE($C$4+1,1,1)) -> 3450 | D11: =SUMIFS(Trabalhos!$K$2:$K$1001,Trabalhos!$A$2:$A$1001,">="&DATE($C$4,IFERROR(MATCH($C$5,Listas!$H$3:$H$14,0),1),1),Trabalhos!$A$2:$A$1001,"<"&DATE($C$4,IFERROR(MATCH($C$5,Listas!$H$3:$H$14,0),12)+1,1)) -> 0 | F11: Abril | G11: =SUMIFS(Trabalhos!$G$2:$G$1001,Trabalhos!$A$2:$A$1001,">="&DATE($C$4,4,1),Trabalhos!$A$2:$A$1001,"<"&DATE($C$4,4+1,1)) -> 5200 | H11: =SUMIFS(Trabalhos!$K$2:$K$1001,Trabalhos!$A$2:$A$1001,">="&DATE($C$4,4,1),Trabalhos!$A$2:$A$1001,"<"&DATE($C$4,4+1,1))+SUMIFS(Trabalhos!$L$2:$L$1001,Trabalhos!$A$2:$A$1001,">="&DATE($C$4,4,1),Trabalhos!$A$2:$A$1001,"<"&DATE($C$4,4+1,1))+SUMIFS(Despesas!$D$2:$D$1001,Despesas!$A$2:$A$1001,">="&DATE($C$4,4,1),Despesas!$A$2:$A$1001,"<"&DATE($C$4,4+1,1)) -> 710 | I11: =G11-H11 -> 4490 | J11: =COUNTIFS(Trabalhos!$A$2:$A$1001,">="&DATE($C$4,4,1),Trabalhos!$A$2:$A$1001,"<"&DATE($C$4,4+1,1)) -> 1 | K11: =COUNTIFS(Orçamentos!$A$2:$A$1001,">="&DATE($C$4,4,1),Orçamentos!$A$2:$A$1001,"<"&DATE($C$4,4+1,1)) -> 3 | L11: =COUNTIFS(Orçamentos!$A$2:$A$1001,">="&DATE($C$4,4,1),Orçamentos!$A$2:$A$1001,"<"&DATE($C$4,4+1,1),Orçamentos!$G$2:$G$1001,"Fechado") -> 2
B12: Outros custos dos trabalhos | C12: =SUMIFS(Trabalhos!$L$2:$L$1001,Trabalhos!$A$2:$A$1001,">="&DATE($C$4,1,1),Trabalhos!$A$2:$A$1001,"<"&DATE($C$4+1,1,1)) -> 820 | D12: =SUMIFS(Trabalhos!$L$2:$L$1001,Trabalhos!$A$2:$A$1001,">="&DATE($C$4,IFERROR(MATCH($C$5,Listas!$H$3:$H$14,0),1),1),Trabalhos!$A$2:$A$1001,"<"&DATE($C$4,IFERROR(MATCH($C$5,Listas!$H$3:$H$14,0),12)+1,1)) -> 50 | F12: Maio | G12: =SUMIFS(Trabalhos!$G$2:$G$1001,Trabalhos!$A$2:$A$1001,">="&DATE($C$4,5,1),Trabalhos!$A$2:$A$1001,"<"&DATE($C$4,5+1,1)) -> 1710 | H12: =SUMIFS(Trabalhos!$K$2:$K$1001,Trabalhos!$A$2:$A$1001,">="&DATE($C$4,5,1),Trabalhos!$A$2:$A$1001,"<"&DATE($C$4,5+1,1))+SUMIFS(Trabalhos!$L$2:$L$1001,Trabalhos!$A$2:$A$1001,">="&DATE($C$4,5,1),Trabalhos!$A$2:$A$1001,"<"&DATE($C$4,5+1,1))+SUMIFS(Despesas!$D$2:$D$1001,Despesas!$A$2:$A$1001,">="&DATE($C$4,5,1),Despesas!$A$2:$A$1001,"<"&DATE($C$4,5+1,1)) -> 60 | I12: =G12-H12 -> 1650 | J12: =COUNTIFS(Trabalhos!$A$2:$A$1001,">="&DATE($C$4,5,1),Trabalhos!$A$2:$A$1001,"<"&DATE($C$4,5+1,1)) -> 2 | K12: =COUNTIFS(Orçamentos!$A$2:$A$1001,">="&DATE($C$4,5,1),Orçamentos!$A$2:$A$1001,"<"&DATE($C$4,5+1,1)) -> 1 | L12: =COUNTIFS(Orçamentos!$A$2:$A$1001,">="&DATE($C$4,5,1),Orçamentos!$A$2:$A$1001,"<"&DATE($C$4,5+1,1),Orçamentos!$G$2:$G$1001,"Fechado") -> 1
B13: Despesas gerais | C13: =SUMIFS(Despesas!$D$2:$D$1001,Despesas!$A$2:$A$1001,">="&DATE($C$4,1,1),Despesas!$A$2:$A$1001,"<"&DATE($C$4+1,1,1)) -> 1580 | D13: =SUMIFS(Despesas!$D$2:$D$1001,Despesas!$A$2:$A$1001,">="&DATE($C$4,IFERROR(MATCH($C$5,Listas!$H$3:$H$14,0),1),1),Despesas!$A$2:$A$1001,"<"&DATE($C$4,IFERROR(MATCH($C$5,Listas!$H$3:$H$14,0),12)+1,1)) -> 60 | F13: Junho | G13: =SUMIFS(Trabalhos!$G$2:$G$1001,Trabalhos!$A$2:$A$1001,">="&DATE($C$4,6,1),Trabalhos!$A$2:$A$1001,"<"&DATE($C$4,6+1,1)) -> 3900 | H13: =SUMIFS(Trabalhos!$K$2:$K$1001,Trabalhos!$A$2:$A$1001,">="&DATE($C$4,6,1),Trabalhos!$A$2:$A$1001,"<"&DATE($C$4,6+1,1))+SUMIFS(Trabalhos!$L$2:$L$1001,Trabalhos!$A$2:$A$1001,">="&DATE($C$4,6,1),Trabalhos!$A$2:$A$1001,"<"&DATE($C$4,6+1,1))+SUMIFS(Despesas!$D$2:$D$1001,Despesas!$A$2:$A$1001,">="&DATE($C$4,6,1),Despesas!$A$2:$A$1001,"<"&DATE($C$4,6+1,1)) -> 850 | I13: =G13-H13 -> 3050 | J13: =COUNTIFS(Trabalhos!$A$2:$A$1001,">="&DATE($C$4,6,1),Trabalhos!$A$2:$A$1001,"<"&DATE($C$4,6+1,1)) -> 1 | K13: =COUNTIFS(Orçamentos!$A$2:$A$1001,">="&DATE($C$4,6,1),Orçamentos!$A$2:$A$1001,"<"&DATE($C$4,6+1,1)) -> 2 | L13: =COUNTIFS(Orçamentos!$A$2:$A$1001,">="&DATE($C$4,6,1),Orçamentos!$A$2:$A$1001,"<"&DATE($C$4,6+1,1),Orçamentos!$G$2:$G$1001,"Fechado") -> 1
B14: LUCRO | C14: =C8-C11-C12-C13 -> 35860 | D14: =D8-D11-D12-D13 -> 3990 | F14: Julho | G14: =SUMIFS(Trabalhos!$G$2:$G$1001,Trabalhos!$A$2:$A$1001,">="&DATE($C$4,7,1),Trabalhos!$A$2:$A$1001,"<"&DATE($C$4,7+1,1)) -> 2400 | H14: =SUMIFS(Trabalhos!$K$2:$K$1001,Trabalhos!$A$2:$A$1001,">="&DATE($C$4,7,1),Trabalhos!$A$2:$A$1001,"<"&DATE($C$4,7+1,1))+SUMIFS(Trabalhos!$L$2:$L$1001,Trabalhos!$A$2:$A$1001,">="&DATE($C$4,7,1),Trabalhos!$A$2:$A$1001,"<"&DATE($C$4,7+1,1))+SUMIFS(Despesas!$D$2:$D$1001,Despesas!$A$2:$A$1001,">="&DATE($C$4,7,1),Despesas!$A$2:$A$1001,"<"&DATE($C$4,7+1,1)) -> 420 | I14: =G14-H14 -> 1980 | J14: =COUNTIFS(Trabalhos!$A$2:$A$1001,">="&DATE($C$4,7,1),Trabalhos!$A$2:$A$1001,"<"&DATE($C$4,7+1,1)) -> 1 | K14: =COUNTIFS(Orçamentos!$A$2:$A$1001,">="&DATE($C$4,7,1),Orçamentos!$A$2:$A$1001,"<"&DATE($C$4,7+1,1)) -> 1 | L14: =COUNTIFS(Orçamentos!$A$2:$A$1001,">="&DATE($C$4,7,1),Orçamentos!$A$2:$A$1001,"<"&DATE($C$4,7+1,1),Orçamentos!$G$2:$G$1001,"Fechado") -> 1
B15: Margem de lucro | C15: =IF(C8=0,0,C14/C8) -> 0.85974586 | D15: =IF(D8=0,0,D14/D8) -> 0.97317073 | F15: Agosto | G15: =SUMIFS(Trabalhos!$G$2:$G$1001,Trabalhos!$A$2:$A$1001,">="&DATE($C$4,8,1),Trabalhos!$A$2:$A$1001,"<"&DATE($C$4,8+1,1)) -> 5600 | H15: =SUMIFS(Trabalhos!$K$2:$K$1001,Trabalhos!$A$2:$A$1001,">="&DATE($C$4,8,1),Trabalhos!$A$2:$A$1001,"<"&DATE($C$4,8+1,1))+SUMIFS(Trabalhos!$L$2:$L$1001,Trabalhos!$A$2:$A$1001,">="&DATE($C$4,8,1),Trabalhos!$A$2:$A$1001,"<"&DATE($C$4,8+1,1))+SUMIFS(Despesas!$D$2:$D$1001,Despesas!$A$2:$A$1001,">="&DATE($C$4,8,1),Despesas!$A$2:$A$1001,"<"&DATE($C$4,8+1,1)) -> 1320 | I15: =G15-H15 -> 4280 | J15: =COUNTIFS(Trabalhos!$A$2:$A$1001,">="&DATE($C$4,8,1),Trabalhos!$A$2:$A$1001,"<"&DATE($C$4,8+1,1)) -> 1 | K15: =COUNTIFS(Orçamentos!$A$2:$A$1001,">="&DATE($C$4,8,1),Orçamentos!$A$2:$A$1001,"<"&DATE($C$4,8+1,1)) -> 2 | L15: =COUNTIFS(Orçamentos!$A$2:$A$1001,">="&DATE($C$4,8,1),Orçamentos!$A$2:$A$1001,"<"&DATE($C$4,8+1,1),Orçamentos!$G$2:$G$1001,"Fechado") -> 1
B16: Trabalhos | C16: =COUNTIFS(Trabalhos!$A$2:$A$1001,">="&DATE($C$4,1,1),Trabalhos!$A$2:$A$1001,"<"&DATE($C$4+1,1,1)) -> 15 | D16: =COUNTIFS(Trabalhos!$A$2:$A$1001,">="&DATE($C$4,IFERROR(MATCH($C$5,Listas!$H$3:$H$14,0),1),1),Trabalhos!$A$2:$A$1001,"<"&DATE($C$4,IFERROR(MATCH($C$5,Listas!$H$3:$H$14,0),12)+1,1)) -> 2 | F16: Setembro | G16: =SUMIFS(Trabalhos!$G$2:$G$1001,Trabalhos!$A$2:$A$1001,">="&DATE($C$4,9,1),Trabalhos!$A$2:$A$1001,"<"&DATE($C$4,9+1,1)) -> 1100 | H16: =SUMIFS(Trabalhos!$K$2:$K$1001,Trabalhos!$A$2:$A$1001,">="&DATE($C$4,9,1),Trabalhos!$A$2:$A$1001,"<"&DATE($C$4,9+1,1))+SUMIFS(Trabalhos!$L$2:$L$1001,Trabalhos!$A$2:$A$1001,">="&DATE($C$4,9,1),Trabalhos!$A$2:$A$1001,"<"&DATE($C$4,9+1,1))+SUMIFS(Despesas!$D$2:$D$1001,Despesas!$A$2:$A$1001,">="&DATE($C$4,9,1),Despesas!$A$2:$A$1001,"<"&DATE($C$4,9+1,1)) -> 350 | I16: =G16-H16 -> 750 | J16: =COUNTIFS(Trabalhos!$A$2:$A$1001,">="&DATE($C$4,9,1),Trabalhos!$A$2:$A$1001,"<"&DATE($C$4,9+1,1)) -> 1 | K16: =COUNTIFS(Orçamentos!$A$2:$A$1001,">="&DATE($C$4,9,1),Orçamentos!$A$2:$A$1001,"<"&DATE($C$4,9+1,1)) -> 3 | L16: =COUNTIFS(Orçamentos!$A$2:$A$1001,">="&DATE($C$4,9,1),Orçamentos!$A$2:$A$1001,"<"&DATE($C$4,9+1,1),Orçamentos!$G$2:$G$1001,"Fechado") -> 2
B17: Valor médio por trabalho | C17: =IF(C16=0,0,C8/C16) -> 2780.6667 | D17: =IF(D16=0,0,D8/D16) -> 2050 | F17: Outubro | G17: =SUMIFS(Trabalhos!$G$2:$G$1001,Trabalhos!$A$2:$A$1001,">="&DATE($C$4,10,1),Trabalhos!$A$2:$A$1001,"<"&DATE($C$4,10+1,1)) -> 4100 | H17: =SUMIFS(Trabalhos!$K$2:$K$1001,Trabalhos!$A$2:$A$1001,">="&DATE($C$4,10,1),Trabalhos!$A$2:$A$1001,"<"&DATE($C$4,10+1,1))+SUMIFS(Trabalhos!$L$2:$L$1001,Trabalhos!$A$2:$A$1001,">="&DATE($C$4,10,1),Trabalhos!$A$2:$A$1001,"<"&DATE($C$4,10+1,1))+SUMIFS(Despesas!$D$2:$D$1001,Despesas!$A$2:$A$1001,">="&DATE($C$4,10,1),Despesas!$A$2:$A$1001,"<"&DATE($C$4,10+1,1)) -> 110 | I17: =G17-H17 -> 3990 | J17: =COUNTIFS(Trabalhos!$A$2:$A$1001,">="&DATE($C$4,10,1),Trabalhos!$A$2:$A$1001,"<"&DATE($C$4,10+1,1)) -> 2 | K17: =COUNTIFS(Orçamentos!$A$2:$A$1001,">="&DATE($C$4,10,1),Orçamentos!$A$2:$A$1001,"<"&DATE($C$4,10+1,1)) -> 2 | L17: =COUNTIFS(Orçamentos!$A$2:$A$1001,">="&DATE($C$4,10,1),Orçamentos!$A$2:$A$1001,"<"&DATE($C$4,10+1,1),Orçamentos!$G$2:$G$1001,"Fechado") -> 1
B18: Orçamentos passados | C18: =COUNTIFS(Orçamentos!$A$2:$A$1001,">="&DATE($C$4,1,1),Orçamentos!$A$2:$A$1001,"<"&DATE($C$4+1,1,1)) -> 20 | D18: =COUNTIFS(Orçamentos!$A$2:$A$1001,">="&DATE($C$4,IFERROR(MATCH($C$5,Listas!$H$3:$H$14,0),1),1),Orçamentos!$A$2:$A$1001,"<"&DATE($C$4,IFERROR(MATCH($C$5,Listas!$H$3:$H$14,0),12)+1,1)) -> 2 | F18: Novembro | G18: =SUMIFS(Trabalhos!$G$2:$G$1001,Trabalhos!$A$2:$A$1001,">="&DATE($C$4,11,1),Trabalhos!$A$2:$A$1001,"<"&DATE($C$4,11+1,1)) -> 6200 | H18: =SUMIFS(Trabalhos!$K$2:$K$1001,Trabalhos!$A$2:$A$1001,">="&DATE($C$4,11,1),Trabalhos!$A$2:$A$1001,"<"&DATE($C$4,11+1,1))+SUMIFS(Trabalhos!$L$2:$L$1001,Trabalhos!$A$2:$A$1001,">="&DATE($C$4,11,1),Trabalhos!$A$2:$A$1001,"<"&DATE($C$4,11+1,1))+SUMIFS(Despesas!$D$2:$D$1001,Despesas!$A$2:$A$1001,">="&DATE($C$4,11,1),Despesas!$A$2:$A$1001,"<"&DATE($C$4,11+1,1)) -> 500 | I18: =G18-H18 -> 5700 | J18: =COUNTIFS(Trabalhos!$A$2:$A$1001,">="&DATE($C$4,11,1),Trabalhos!$A$2:$A$1001,"<"&DATE($C$4,11+1,1)) -> 1 | K18: =COUNTIFS(Orçamentos!$A$2:$A$1001,">="&DATE($C$4,11,1),Orçamentos!$A$2:$A$1001,"<"&DATE($C$4,11+1,1)) -> 1 | L18: =COUNTIFS(Orçamentos!$A$2:$A$1001,">="&DATE($C$4,11,1),Orçamentos!$A$2:$A$1001,"<"&DATE($C$4,11+1,1),Orçamentos!$G$2:$G$1001,"Fechado") -> 1
B19: Orçamentos fechados | C19: =COUNTIFS(Orçamentos!$A$2:$A$1001,">="&DATE($C$4,1,1),Orçamentos!$A$2:$A$1001,"<"&DATE($C$4+1,1,1),Orçamentos!$G$2:$G$1001,"Fechado") -> 14 | D19: =COUNTIFS(Orçamentos!$A$2:$A$1001,">="&DATE($C$4,IFERROR(MATCH($C$5,Listas!$H$3:$H$14,0),1),1),Orçamentos!$A$2:$A$1001,"<"&DATE($C$4,IFERROR(MATCH($C$5,Listas!$H$3:$H$14,0),12)+1,1),Orçamentos!$G$2:$G$1001,"Fechado") -> 1 | F19: Dezembro | G19: =SUMIFS(Trabalhos!$G$2:$G$1001,Trabalhos!$A$2:$A$1001,">="&DATE($C$4,12,1),Trabalhos!$A$2:$A$1001,"<"&DATE($C$4,12+1,1)) -> 1100 | H19: =SUMIFS(Trabalhos!$K$2:$K$1001,Trabalhos!$A$2:$A$1001,">="&DATE($C$4,12,1),Trabalhos!$A$2:$A$1001,"<"&DATE($C$4,12+1,1))+SUMIFS(Trabalhos!$L$2:$L$1001,Trabalhos!$A$2:$A$1001,">="&DATE($C$4,12,1),Trabalhos!$A$2:$A$1001,"<"&DATE($C$4,12+1,1))+SUMIFS(Despesas!$D$2:$D$1001,Despesas!$A$2:$A$1001,">="&DATE($C$4,12,1),Despesas!$A$2:$A$1001,"<"&DATE($C$4,12+1,1)) -> 0 | I19: =G19-H19 -> 1100 | J19: =COUNTIFS(Trabalhos!$A$2:$A$1001,">="&DATE($C$4,12,1),Trabalhos!$A$2:$A$1001,"<"&DATE($C$4,12+1,1)) -> 1 | K19: =COUNTIFS(Orçamentos!$A$2:$A$1001,">="&DATE($C$4,12,1),Orçamentos!$A$2:$A$1001,"<"&DATE($C$4,12+1,1)) -> 0 | L19: =COUNTIFS(Orçamentos!$A$2:$A$1001,">="&DATE($C$4,12,1),Orçamentos!$A$2:$A$1001,"<"&DATE($C$4,12+1,1),Orçamentos!$G$2:$G$1001,"Fechado") -> 0
B20: Taxa de fechamento | C20: =IF(C18=0,0,C19/C18) -> 0.7 | D20: =IF(D18=0,0,D19/D18) -> 0.5 | F20: TOTAL DO ANO | G20: =SUM(G8:G19) -> 41710 | H20: =SUM(H8:H19) -> 5850 | I20: =SUM(I8:I19) -> 35860 | J20: =SUM(J8:J19) -> 15 | K20: =SUM(K8:K19) -> 20 | L20: =SUM(L8:L19) -> 14
D21: =IF(ISNA(MATCH($C$5,Listas!$H$3:$H$14,0)),"Escolha um mês na célula C5","")
B24: Por tipo de serviço (ano escolhido)
B25: Tipo de serviço | C25: Trabalhos | D25: Faturamento | F25: Valor médio | G25: Lucro | H25: Orçamentos | I25: Taxa fech.
B26: =Listas!$A$2 -> Casamento | C26: =COUNTIFS(Trabalhos!$A$2:$A$1001,">="&DATE($C$4,1,1),Trabalhos!$A$2:$A$1001,"<"&DATE($C$4+1,1,1),Trabalhos!$D$2:$D$1001,$B26) -> 5 | D26: =SUMIFS(Trabalhos!$G$2:$G$1001,Trabalhos!$A$2:$A$1001,">="&DATE($C$4,1,1),Trabalhos!$A$2:$A$1001,"<"&DATE($C$4+1,1,1),Trabalhos!$D$2:$D$1001,$B26) -> 25700 | F26: =IF(C26=0,0,D26/C26) -> 5140 | G26: =D26-SUMIFS(Trabalhos!$K$2:$K$1001,Trabalhos!$A$2:$A$1001,">="&DATE($C$4,1,1),Trabalhos!$A$2:$A$1001,"<"&DATE($C$4+1,1,1),Trabalhos!$D$2:$D$1001,$B26)-SUMIFS(Trabalhos!$L$2:$L$1001,Trabalhos!$A$2:$A$1001,">="&DATE($C$4,1,1),Trabalhos!$A$2:$A$1001,"<"&DATE($C$4+1,1,1),Trabalhos!$D$2:$D$1001,$B26) -> 22410 | H26: =COUNTIFS(Orçamentos!$A$2:$A$1001,">="&DATE($C$4,1,1),Orçamentos!$A$2:$A$1001,"<"&DATE($C$4+1,1,1),Orçamentos!$C$2:$C$1001,$B26) -> 6 | I26: =IF(H26=0,0,COUNTIFS(Orçamentos!$A$2:$A$1001,">="&DATE($C$4,1,1),Orçamentos!$A$2:$A$1001,"<"&DATE($C$4+1,1,1),Orçamentos!$C$2:$C$1001,$B26,Orçamentos!$G$2:$G$1001,"Fechado")/H26) -> 0.66666667
B27: =Listas!$A$3 -> Aniversário | C27: =COUNTIFS(Trabalhos!$A$2:$A$1001,">="&DATE($C$4,1,1),Trabalhos!$A$2:$A$1001,"<"&DATE($C$4+1,1,1),Trabalhos!$D$2:$D$1001,$B27) -> 3 | D27: =SUMIFS(Trabalhos!$G$2:$G$1001,Trabalhos!$A$2:$A$1001,">="&DATE($C$4,1,1),Trabalhos!$A$2:$A$1001,"<"&DATE($C$4+1,1,1),Trabalhos!$D$2:$D$1001,$B27) -> 4700 | F27: =IF(C27=0,0,D27/C27) -> 1566.6667 | G27: =D27-SUMIFS(Trabalhos!$K$2:$K$1001,Trabalhos!$A$2:$A$1001,">="&DATE($C$4,1,1),Trabalhos!$A$2:$A$1001,"<"&DATE($C$4+1,1,1),Trabalhos!$D$2:$D$1001,$B27)-SUMIFS(Trabalhos!$L$2:$L$1001,Trabalhos!$A$2:$A$1001,">="&DATE($C$4,1,1),Trabalhos!$A$2:$A$1001,"<"&DATE($C$4+1,1,1),Trabalhos!$D$2:$D$1001,$B27) -> 4300 | H27: =COUNTIFS(Orçamentos!$A$2:$A$1001,">="&DATE($C$4,1,1),Orçamentos!$A$2:$A$1001,"<"&DATE($C$4+1,1,1),Orçamentos!$C$2:$C$1001,$B27) -> 4 | I27: =IF(H27=0,0,COUNTIFS(Orçamentos!$A$2:$A$1001,">="&DATE($C$4,1,1),Orçamentos!$A$2:$A$1001,"<"&DATE($C$4+1,1,1),Orçamentos!$C$2:$C$1001,$B27,Orçamentos!$G$2:$G$1001,"Fechado")/H27) -> 0.75
B28: =Listas!$A$4 -> Edição | C28: =COUNTIFS(Trabalhos!$A$2:$A$1001,">="&DATE($C$4,1,1),Trabalhos!$A$2:$A$1001,"<"&DATE($C$4+1,1,1),Trabalhos!$D$2:$D$1001,$B28) -> 1 | D28: =SUMIFS(Trabalhos!$G$2:$G$1001,Trabalhos!$A$2:$A$1001,">="&DATE($C$4,1,1),Trabalhos!$A$2:$A$1001,"<"&DATE($C$4+1,1,1),Trabalhos!$D$2:$D$1001,$B28) -> 960 | F28: =IF(C28=0,0,D28/C28) -> 960 | G28: =D28-SUMIFS(Trabalhos!$K$2:$K$1001,Trabalhos!$A$2:$A$1001,">="&DATE($C$4,1,1),Trabalhos!$A$2:$A$1001,"<"&DATE($C$4+1,1,1),Trabalhos!$D$2:$D$1001,$B28)-SUMIFS(Trabalhos!$L$2:$L$1001,Trabalhos!$A$2:$A$1001,">="&DATE($C$4,1,1),Trabalhos!$A$2:$A$1001,"<"&DATE($C$4+1,1,1),Trabalhos!$D$2:$D$1001,$B28) -> 960 | H28: =COUNTIFS(Orçamentos!$A$2:$A$1001,">="&DATE($C$4,1,1),Orçamentos!$A$2:$A$1001,"<"&DATE($C$4+1,1,1),Orçamentos!$C$2:$C$1001,$B28) -> 2 | I28: =IF(H28=0,0,COUNTIFS(Orçamentos!$A$2:$A$1001,">="&DATE($C$4,1,1),Orçamentos!$A$2:$A$1001,"<"&DATE($C$4+1,1,1),Orçamentos!$C$2:$C$1001,$B28,Orçamentos!$G$2:$G$1001,"Fechado")/H28) -> 0.5
B29: =Listas!$A$5 -> Vídeo institucional | C29: =COUNTIFS(Trabalhos!$A$2:$A$1001,">="&DATE($C$4,1,1),Trabalhos!$A$2:$A$1001,"<"&DATE($C$4+1,1,1),Trabalhos!$D$2:$D$1001,$B29) -> 2 | D29: =SUMIFS(Trabalhos!$G$2:$G$1001,Trabalhos!$A$2:$A$1001,">="&DATE($C$4,1,1),Trabalhos!$A$2:$A$1001,"<"&DATE($C$4+1,1,1),Trabalhos!$D$2:$D$1001,$B29) -> 6300 | F29: =IF(C29=0,0,D29/C29) -> 3150 | G29: =D29-SUMIFS(Trabalhos!$K$2:$K$1001,Trabalhos!$A$2:$A$1001,">="&DATE($C$4,1,1),Trabalhos!$A$2:$A$1001,"<"&DATE($C$4+1,1,1),Trabalhos!$D$2:$D$1001,$B29)-SUMIFS(Trabalhos!$L$2:$L$1001,Trabalhos!$A$2:$A$1001,">="&DATE($C$4,1,1),Trabalhos!$A$2:$A$1001,"<"&DATE($C$4+1,1,1),Trabalhos!$D$2:$D$1001,$B29) -> 5790 | H29: =COUNTIFS(Orçamentos!$A$2:$A$1001,">="&DATE($C$4,1,1),Orçamentos!$A$2:$A$1001,"<"&DATE($C$4+1,1,1),Orçamentos!$C$2:$C$1001,$B29) -> 3 | I29: =IF(H29=0,0,COUNTIFS(Orçamentos!$A$2:$A$1001,">="&DATE($C$4,1,1),Orçamentos!$A$2:$A$1001,"<"&DATE($C$4+1,1,1),Orçamentos!$C$2:$C$1001,$B29,Orçamentos!$G$2:$G$1001,"Fechado")/H29) -> 0.66666667
B30: =Listas!$A$6 -> Storymaker | C30: =COUNTIFS(Trabalhos!$A$2:$A$1001,">="&DATE($C$4,1,1),Trabalhos!$A$2:$A$1001,"<"&DATE($C$4+1,1,1),Trabalhos!$D$2:$D$1001,$B30) -> 1 | D30: =SUMIFS(Trabalhos!$G$2:$G$1001,Trabalhos!$A$2:$A$1001,">="&DATE($C$4,1,1),Trabalhos!$A$2:$A$1001,"<"&DATE($C$4+1,1,1),Trabalhos!$D$2:$D$1001,$B30) -> 1100 | F30: =IF(C30=0,0,D30/C30) -> 1100 | G30: =D30-SUMIFS(Trabalhos!$K$2:$K$1001,Trabalhos!$A$2:$A$1001,">="&DATE($C$4,1,1),Trabalhos!$A$2:$A$1001,"<"&DATE($C$4+1,1,1),Trabalhos!$D$2:$D$1001,$B30)-SUMIFS(Trabalhos!$L$2:$L$1001,Trabalhos!$A$2:$A$1001,">="&DATE($C$4,1,1),Trabalhos!$A$2:$A$1001,"<"&DATE($C$4+1,1,1),Trabalhos!$D$2:$D$1001,$B30) -> 1060 | H30: =COUNTIFS(Orçamentos!$A$2:$A$1001,">="&DATE($C$4,1,1),Orçamentos!$A$2:$A$1001,"<"&DATE($C$4+1,1,1),Orçamentos!$C$2:$C$1001,$B30) -> 1 | I30: =IF(H30=0,0,COUNTIFS(Orçamentos!$A$2:$A$1001,">="&DATE($C$4,1,1),Orçamentos!$A$2:$A$1001,"<"&DATE($C$4+1,1,1),Orçamentos!$C$2:$C$1001,$B30,Orçamentos!$G$2:$G$1001,"Fechado")/H30) -> 1
B31: =Listas!$A$7 -> Fotografia | C31: =COUNTIFS(Trabalhos!$A$2:$A$1001,">="&DATE($C$4,1,1),Trabalhos!$A$2:$A$1001,"<"&DATE($C$4+1,1,1),Trabalhos!$D$2:$D$1001,$B31) -> 1 | D31: =SUMIFS(Trabalhos!$G$2:$G$1001,Trabalhos!$A$2:$A$1001,">="&DATE($C$4,1,1),Trabalhos!$A$2:$A$1001,"<"&DATE($C$4+1,1,1),Trabalhos!$D$2:$D$1001,$B31) -> 750 | F31: =IF(C31=0,0,D31/C31) -> 750 | G31: =D31-SUMIFS(Trabalhos!$K$2:$K$1001,Trabalhos!$A$2:$A$1001,">="&DATE($C$4,1,1),Trabalhos!$A$2:$A$1001,"<"&DATE($C$4+1,1,1),Trabalhos!$D$2:$D$1001,$B31)-SUMIFS(Trabalhos!$L$2:$L$1001,Trabalhos!$A$2:$A$1001,">="&DATE($C$4,1,1),Trabalhos!$A$2:$A$1001,"<"&DATE($C$4+1,1,1),Trabalhos!$D$2:$D$1001,$B31) -> 750 | H31: =COUNTIFS(Orçamentos!$A$2:$A$1001,">="&DATE($C$4,1,1),Orçamentos!$A$2:$A$1001,"<"&DATE($C$4+1,1,1),Orçamentos!$C$2:$C$1001,$B31) -> 2 | I31: =IF(H31=0,0,COUNTIFS(Orçamentos!$A$2:$A$1001,">="&DATE($C$4,1,1),Orçamentos!$A$2:$A$1001,"<"&DATE($C$4+1,1,1),Orçamentos!$C$2:$C$1001,$B31,Orçamentos!$G$2:$G$1001,"Fechado")/H31) -> 0.5
B32: =Listas!$A$8 -> Chá revelação | C32: =COUNTIFS(Trabalhos!$A$2:$A$1001,">="&DATE($C$4,1,1),Trabalhos!$A$2:$A$1001,"<"&DATE($C$4+1,1,1),Trabalhos!$D$2:$D$1001,$B32) -> 2 | D32: =SUMIFS(Trabalhos!$G$2:$G$1001,Trabalhos!$A$2:$A$1001,">="&DATE($C$4,1,1),Trabalhos!$A$2:$A$1001,"<"&DATE($C$4+1,1,1),Trabalhos!$D$2:$D$1001,$B32) -> 2200 | F32: =IF(C32=0,0,D32/C32) -> 1100 | G32: =D32-SUMIFS(Trabalhos!$K$2:$K$1001,Trabalhos!$A$2:$A$1001,">="&DATE($C$4,1,1),Trabalhos!$A$2:$A$1001,"<"&DATE($C$4+1,1,1),Trabalhos!$D$2:$D$1001,$B32)-SUMIFS(Trabalhos!$L$2:$L$1001,Trabalhos!$A$2:$A$1001,">="&DATE($C$4,1,1),Trabalhos!$A$2:$A$1001,"<"&DATE($C$4+1,1,1),Trabalhos!$D$2:$D$1001,$B32) -> 2170 | H32: =COUNTIFS(Orçamentos!$A$2:$A$1001,">="&DATE($C$4,1,1),Orçamentos!$A$2:$A$1001,"<"&DATE($C$4+1,1,1),Orçamentos!$C$2:$C$1001,$B32) -> 2 | I32: =IF(H32=0,0,COUNTIFS(Orçamentos!$A$2:$A$1001,">="&DATE($C$4,1,1),Orçamentos!$A$2:$A$1001,"<"&DATE($C$4+1,1,1),Orçamentos!$C$2:$C$1001,$B32,Orçamentos!$G$2:$G$1001,"Fechado")/H32) -> 1
B33: =Listas!$A$9 -> Outro | C33: =COUNTIFS(Trabalhos!$A$2:$A$1001,">="&DATE($C$4,1,1),Trabalhos!$A$2:$A$1001,"<"&DATE($C$4+1,1,1),Trabalhos!$D$2:$D$1001,$B33) -> 0 | D33: =SUMIFS(Trabalhos!$G$2:$G$1001,Trabalhos!$A$2:$A$1001,">="&DATE($C$4,1,1),Trabalhos!$A$2:$A$1001,"<"&DATE($C$4+1,1,1),Trabalhos!$D$2:$D$1001,$B33) -> 0 | F33: =IF(C33=0,0,D33/C33) -> 0 | G33: =D33-SUMIFS(Trabalhos!$K$2:$K$1001,Trabalhos!$A$2:$A$1001,">="&DATE($C$4,1,1),Trabalhos!$A$2:$A$1001,"<"&DATE($C$4+1,1,1),Trabalhos!$D$2:$D$1001,$B33)-SUMIFS(Trabalhos!$L$2:$L$1001,Trabalhos!$A$2:$A$1001,">="&DATE($C$4,1,1),Trabalhos!$A$2:$A$1001,"<"&DATE($C$4+1,1,1),Trabalhos!$D$2:$D$1001,$B33) -> 0 | H33: =COUNTIFS(Orçamentos!$A$2:$A$1001,">="&DATE($C$4,1,1),Orçamentos!$A$2:$A$1001,"<"&DATE($C$4+1,1,1),Orçamentos!$C$2:$C$1001,$B33) -> 0 | I33: =IF(H33=0,0,COUNTIFS(Orçamentos!$A$2:$A$1001,">="&DATE($C$4,1,1),Orçamentos!$A$2:$A$1001,"<"&DATE($C$4+1,1,1),Orçamentos!$C$2:$C$1001,$B33,Orçamentos!$G$2:$G$1001,"Fechado")/H33) -> 0

Sheet Trabalhos
A1: Data do evento | B1: Horário | C1: Cliente | D1: Tipo de serviço | E1: O que foi fechado | F1: Local / cidade | G1: Valor fechado | H1: Valor recebido | I1: Forma de pagamento | J1: Freelancers | K1: Custo com freelancers | L1: Outros custos do trabalho | M1: A receber | N1: Lucro | O1: Pagamento | P1: Observações
A2: 46046 | B2: 0.66666667 | C2: Cliente Exemplo 1 | D2: Casamento | E2: Teaser + filme completo + 10 reels | F2: Campinas | G2: 4800 | H2: 4800 | I2: Pix | J2: Freela A (2ª câmera) | K2: 500 | L2: 120 | M2: =IF(G2="","",G2-N(H2)) -> 0 | N2: =IF(G2="","",G2-N(K2)-N(L2)) -> 4180 | O2: =IF(G2="","",IF(N(H2)>=G2,"Pago",IF(N(H2)>0,"Parcial","Pendente"))) -> Pago | P2: EXEMPLO
A3: 46067 | B3: 0.83333333 | C3: Cliente Exemplo 2 | D3: Aniversário | E3: Storymaker 4h + teaser | F3: Valinhos | G3: 1200 | H3: 1200 | I3: Pix | K3: 0 | L3: 40 | M3: =IF(G3="","",G3-N(H3)) -> 0 | N3: =IF(G3="","",G3-N(K3)-N(L3)) -> 1160 | O3: =IF(G3="","",IF(N(H3)>=G3,"Pago",IF(N(H3)>0,"Parcial","Pendente"))) -> Pago | P3: EXEMPLO
A4: 46088 | B4: 0.375 | C4: Empresa Exemplo | D4: Vídeo institucional | E4: Vídeo institucional 2 min + 3 cortes para redes | F4: Campinas | G4: 3500 | H4: 3500 | I4: Transferência | J4: Freela B (drone) | K4: 400 | L4: 60 | M4: =IF(G4="","",G4-N(H4)) -> 0 | N4: =IF(G4="","",G4-N(K4)-N(L4)) -> 3040 | O4: =IF(G4="","",IF(N(H4)>=G4,"Pago",IF(N(H4)>0,"Parcial","Pendente"))) -> Pago | P4: EXEMPLO
A5: 46102 | B5: 0.625 | C5: Cliente Exemplo 3 | D5: Chá revelação | E5: Storymaker + vídeo da revelação | F5: Hortolândia | G5: 900 | H5: 900 | I5: Pix | K5: 0 | L5: 30 | M5: =IF(G5="","",G5-N(H5)) -> 0 | N5: =IF(G5="","",G5-N(K5)-N(L5)) -> 870 | O5: =IF(G5="","",IF(N(H5)>=G5,"Pago",IF(N(H5)>0,"Parcial","Pendente"))) -> Pago | P5: EXEMPLO
A6: 46123 | B6: 0.70833333 | C6: Cliente Exemplo 4 | D6: Casamento | E6: Filme completo + cerimônia na íntegra | F6: Indaiatuba | G6: 5200 | H6: 5200 | I6: Parcelado | J6: Freela A (2ª câmera) | K6: 500 | L6: 150 | M6: =IF(G6="","",G6-N(H6)) -> 0 | N6: =IF(G6="","",G6-N(K6)-N(L6)) -> 4550 | O6: =IF(G6="","",IF(N(H6)>=G6,"Pago",IF(N(H6)>0,"Parcial","Pendente"))) -> Pago | P6: EXEMPLO
A7: 46145 | B7: 0.41666667 | C7: Cliente Exemplo 5 | D7: Fotografia | E7: Ensaio externo · 60 fotos editadas | F7: Campinas | G7: 750 | H7: 750 | I7: Pix | K7: 0 | L7: 0 | M7: =IF(G7="","",G7-N(H7)) -> 0 | N7: =IF(G7="","",G7-N(K7)-N(L7)) -> 750 | O7: =IF(G7="","",IF(N(H7)>=G7,"Pago",IF(N(H7)>0,"Parcial","Pendente"))) -> Pago | P7: EXEMPLO
A8: 46162 | C8: Empresa Exemplo | D8: Edição | E8: Edição de 8 reels | F8: Remoto | G8: 960 | H8: 960 | I8: Pix | K8: 0 | L8: 0 | M8: =IF(G8="","",G8-N(H8)) -> 0 | N8: =IF(G8="","",G8-N(K8)-N(L8)) -> 960 | O8: =IF(G8="","",IF(N(H8)>=G8,"Pago",IF(N(H8)>0,"Parcial","Pendente"))) -> Pago | P8: EXEMPLO
A9: 46186 | B9: 0.79166667 | C9: Cliente Exemplo 6 | D9: Casamento | E9: Teaser + storymaker + 15 reels | F9: Sumaré | G9: 3900 | H9: 3900 | I9: Pix | J9: Freela C (storymaker) | K9: 350 | L9: 90 | M9: =IF(G9="","",G9-N(H9)) -> 0 | N9: =IF(G9="","",G9-N(K9)-N(L9)) -> 3460 | O9: =IF(G9="","",IF(N(H9)>=G9,"Pago",IF(N(H9)>0,"Parcial","Pendente"))) -> Pago | P9: EXEMPLO
A10: 46221 | B10: 0.875 | C10: Cliente Exemplo 7 | D10: Aniversário | E10: Festa 15 anos · teaser + filme | F10: Campinas | G10: 2400 | H10: 2400 | I10: Cartão de crédito | J10: Freela C (storymaker) | K10: 300 | L10: 60 | M10: =IF(G10="","",G10-N(H10)) -> 0 | N10: =IF(G10="","",G10-N(K10)-N(L10)) -> 2040 | O10: =IF(G10="","",IF(N(H10)>=G10,"Pago",IF(N(H10)>0,"Parcial","Pendente"))) -> Pago | P10: EXEMPLO
A11: 46256 | B11: 0.6875 | C11: Cliente Exemplo 8 | D11: Casamento | E11: Teaser + filme completo + drone | F11: Jaguariúna | G11: 5600 | H11: 5600 | I11: Parcelado | J11: Freela A, Freela B | K11: 900 | L11: 180 | M11: =IF(G11="","",G11-N(H11)) -> 0 | N11: =IF(G11="","",G11-N(K11)-N(L11)) -> 4520 | O11: =IF(G11="","",IF(N(H11)>=G11,"Pago",IF(N(H11)>0,"Parcial","Pendente"))) -> Pago | P11: EXEMPLO
A12: 46277 | B12: 0.58333333 | C12: Cliente Exemplo 9 | D12: Storymaker | E12: Storymaker 6h · 20 stories só para o casal | F12: Campinas | G12: 1100 | H12: 1100 | I12: Pix | K12: 0 | L12: 40 | M12: =IF(G12="","",G12-N(H12)) -> 0 | N12: =IF(G12="","",G12-N(K12)-N(L12)) -> 1060 | O12: =IF(G12="","",IF(N(H12)>=G12,"Pago",IF(N(H12)>0,"Parcial","Pendente"))) -> Pago | P12: EXEMPLO
A13: 46298 | B13: 0.375 | C13: Empresa Exemplo 2 | D13: Vídeo institucional | E13: Vídeo de lançamento + 5 reels | F13: Paulínia | G13: 2800 | H13: 1400 | I13: Transferência | K13: 0 | L13: 50 | M13: =IF(G13="","",G13-N(H13)) -> 1400 | N13: =IF(G13="","",G13-N(K13)-N(L13)) -> 2750 | O13: =IF(G13="","",IF(N(H13)>=G13,"Pago",IF(N(H13)>0,"Parcial","Pendente"))) -> Parcial | P13: EXEMPLO
A14: 46320 | B14: 0.625 | C14: Cliente Exemplo 10 | D14: Chá revelação | E14: Teaser + fotos da revelação | F14: Valinhos | G14: 1300 | H14: 650 | I14: Pix | K14: 0 | L14: 0 | M14: =IF(G14="","",G14-N(H14)) -> 650 | N14: =IF(G14="","",G14-N(K14)-N(L14)) -> 1300 | O14: =IF(G14="","",IF(N(H14)>=G14,"Pago",IF(N(H14)>0,"Parcial","Pendente"))) -> Parcial | P14: EXEMPLO
A15: 46347 | B15: 0.70833333 | C15: Cliente Exemplo 11 | D15: Casamento | E15: Filme completo + teaser + storymaker | F15: Campinas | G15: 6200 | H15: 3100 | I15: Parcelado | J15: Freela A (2ª câmera) | K15: 500 | L15: 0 | M15: =IF(G15="","",G15-N(H15)) -> 3100 | N15: =IF(G15="","",G15-N(K15)-N(L15)) -> 5700 | O15: =IF(G15="","",IF(N(H15)>=G15,"Pago",IF(N(H15)>0,"Parcial","Pendente"))) -> Parcial | P15: EXEMPLO
A16: 46368 | B16: 0.83333333 | C16: Cliente Exemplo 12 | D16: Aniversário | E16: Storymaker 4h | F16: Americana | G16: 1100 | H16: 0 | I16: Pix | K16: 0 | L16: 0 | M16: =IF(G16="","",G16-N(H16)) -> 1100 | N16: =IF(G16="","",G16-N(K16)-N(L16)) -> 1100 | O16: =IF(G16="","",IF(N(H16)>=G16,"Pago",IF(N(H16)>0,"Parcial","Pendente"))) -> Pendente | P16: EXEMPLO
M17: =IF(G17="","",G17-N(H17)) | N17: =IF(G17="","",G17-N(K17)-N(L17)) | O17: =IF(G17="","",IF(N(H17)>=G17,"Pago",IF(N(H17)>0,"Parcial","Pendente")))
M18: =IF(G18="","",G18-N(H18)) | N18: =IF(G18="","",G18-N(K18)-N(L18)) | O18: =IF(G18="","",IF(N(H18)>=G18,"Pago",IF(N(H18)>0,"Parcial","Pendente")))
M19: =IF(G19="","",G19-N(H19)) | N19: =IF(G19="","",G19-N(K19)-N(L19)) | O19: =IF(G19="","",IF(N(H19)>=G19,"Pago",IF(N(H19)>0,"Parcial","Pendente")))
M20: =IF(G20="","",G20-N(H20)) | N20: =IF(G20="","",G20-N(K20)-N(L20)) | O20: =IF(G20="","",IF(N(H20)>=G20,"Pago",IF(N(H20)>0,"Parcial","Pendente")))
M21: =IF(G21="","",G21-N(H21)) | N21: =IF(G21="","",G21-N(K21)-N(L21)) | O21: =IF(G21="","",IF(N(H21)>=G21,"Pago",IF(N(H21)>0,"Parcial","Pendente")))
M22: =IF(G22="","",G22-N(H22)) | N22: =IF(G22="","",G22-N(K22)-N(L22)) | O22: =IF(G22="","",IF(N(H22)>=G22,"Pago",IF(N(H22)>0,"Parcial","Pendente")))
M23: =IF(G23="","",G23-N(H23)) | N23: =IF(G23="","",G23-N(K23)-N(L23)) | O23: =IF(G23="","",IF(N(H23)>=G23,"Pago",IF(N(H23)>0,"Parcial","Pendente")))
M24: =IF(G24="","",G24-N(H24)) | N24: =IF(G24="","",G24-N(K24)-N(L24)) | O24: =IF(G24="","",IF(N(H24)>=G24,"Pago",IF(N(H24)>0,"Parcial","Pendente")))
M25: =IF(G25="","",G25-N(H25)) | N25: =IF(G25="","",G25-N(K25)-N(L25)) | O25: =IF(G25="","",IF(N(H25)>=G25,"Pago",IF(N(H25)>0,"Parcial","Pendente")))
M26: =IF(G26="","",G26-N(H26)) | N26: =IF(G26="","",G26-N(K26)-N(L26)) | O26: =IF(G26="","",IF(N(H26)>=G26,"Pago",IF(N(H26)>0,"Parcial","Pendente")))
M27: =IF(G27="","",G27-N(H27)) | N27: =IF(G27="","",G27-N(K27)-N(L27)) | O27: =IF(G27="","",IF(N(H27)>=G27,"Pago",IF(N(H27)>0,"Parcial","Pendente")))
M28: =IF(G28="","",G28-N(H28)) | N28: =IF(G28="","",G28-N(K28)-N(L28)) | O28: =IF(G28="","",IF(N(H28)>=G28,"Pago",IF(N(H28)>0,"Parcial","Pendente")))
... M1001: =IF(G1001="","",G1001-N(H1001)) | N1001: =IF(G1001="","",G1001-N(K1001)-N(L1001)) | O1001: =IF(G1001="","",IF(N(H1001)>=G1001,"Pago",IF(N(H1001)>0,"Parcial","Pendente")))

Sheet Orçamentos
A1: Data do envio | B1: Cliente | C1: Tipo de serviço | D1: O que foi orçado | E1: Data do evento | F1: Valor orçado | G1: Status | H1: Motivo / observações
A2: 46015 | B2: Cliente Exemplo 1 | C2: Casamento | D2: Teaser + filme completo + 10 reels | E2: 46046 | F2: 4800 | G2: Fechado | H2: EXEMPLO
A3: 46036 | B3: Cliente Exemplo 2 | C3: Aniversário | D3: Storymaker 4h + teaser | E3: 46067 | F3: 1200 | G3: Fechado | H3: EXEMPLO
A4: 46055 | B4: Cliente Exemplo 13 | C4: Casamento | D4: Teaser + filme completo | E4: 46179 | F4: 6500 | G4: Recusado | H4: EXEMPLO · achou caro
A5: 46060 | B5: Empresa Exemplo | C5: Vídeo institucional | D5: Vídeo institucional 2 min + 3 cortes para redes | E5: 46088 | F5: 3500 | G5: Fechado | H5: EXEMPLO
A6: 46074 | B6: Cliente Exemplo 3 | C6: Chá revelação | D6: Storymaker + vídeo da revelação | E6: 46102 | F6: 900 | G6: Fechado | H6: EXEMPLO
A7: 46092 | B7: Cliente Exemplo 4 | C7: Casamento | D7: Filme completo + cerimônia na íntegra | E7: 46123 | F7: 5200 | G7: Fechado | H7: EXEMPLO
A8: 46115 | B8: Cliente Exemplo 5 | C8: Fotografia | D8: Ensaio externo · 60 fotos editadas | E8: 46145 | F8: 750 | G8: Fechado | H8: EXEMPLO
A9: 46127 | B9: Cliente Exemplo 14 | C9: Aniversário | D9: Storymaker 3h | E9: 46172 | F9: 900 | G9: Recusado | H9: EXEMPLO · data ocupada
A10: 46132 | B10: Empresa Exemplo | C10: Edição | D10: Edição de 8 reels | E10: 46162 | F10: 960 | G10: Fechado | H10: EXEMPLO
A11: 46155 | B11: Cliente Exemplo 6 | C11: Casamento | D11: Teaser + storymaker + 15 reels | E11: 46186 | F11: 3900 | G11: Fechado | H11: EXEMPLO
A12: 46175 | B12: Empresa Exemplo 3 | C12: Vídeo institucional | D12: Vídeo institucional 1 min | E12: 46213 | F12: 2500 | G12: Recusado | H12: EXEMPLO · fechou com outro
A13: 46191 | B13: Cliente Exemplo 7 | C13: Aniversário | D13: Festa 15 anos · teaser + filme | E13: 46221 | F13: 2400 | G13: Fechado | H13: EXEMPLO
... A22: 46338 | B22: Cliente Exemplo 12 | C22: Aniversário | D22: Storymaker 4h | E22: 46368 | F22: 1100 | G22: Fechado | H22: EXEMPLO

Sheet Clientes
A1: Nome | B1: WhatsApp | C1: Instagram | D1: Cidade | E1: Como conheceu | F1: Trabalhos | G1: Total fechado | H1: Observações
A2: Cliente Exemplo 1 | B2: (19) 90000-0001 | D2: Campinas | E2: Instagram | F2: =IF(A2="","",COUNTIF(Trabalhos!$C$2:$C$1001,A2)) -> 1 | G2: =IF(A2="","",SUMIFS(Trabalhos!$G$2:$G$1001,Trabalhos!$C$2:$C$1001,A2)) -> 4800 | H2: EXEMPLO
A3: Cliente Exemplo 2 | B3: (19) 90000-0002 | D3: Valinhos | E3: Indicação | F3: =IF(A3="","",COUNTIF(Trabalhos!$C$2:$C$1001,A3)) -> 1 | G3: =IF(A3="","",SUMIFS(Trabalhos!$G$2:$G$1001,Trabalhos!$C$2:$C$1001,A3)) -> 1200 | H3: EXEMPLO
A4: Empresa Exemplo | B4: (19) 90000-0003 | D4: Campinas | E4: Instagram | F4: =IF(A4="","",COUNTIF(Trabalhos!$C$2:$C$1001,A4)) -> 2 | G4: =IF(A4="","",SUMIFS(Trabalhos!$G$2:$G$1001,Trabalhos!$C$2:$C$1001,A4)) -> 4460 | H4: EXEMPLO
A5: Cliente Exemplo 3 | B5: (19) 90000-0004 | D5: Hortolândia | E5: Site | F5: =IF(A5="","",COUNTIF(Trabalhos!$C$2:$C$1001,A5)) -> 1 | G5: =IF(A5="","",SUMIFS(Trabalhos!$G$2:$G$1001,Trabalhos!$C$2:$C$1001,A5)) -> 900 | H5: EXEMPLO
A6: Cliente Exemplo 4 | B6: (19) 90000-0005 | D6: Indaiatuba | E6: Indicação | F6: =IF(A6="","",COUNTIF(Trabalhos!$C$2:$C$1001,A6)) -> 1 | G6: =IF(A6="","",SUMIFS(Trabalhos!$G$2:$G$1001,Trabalhos!$C$2:$C$1001,A6)) -> 5200 | H6: EXEMPLO
A7: Cliente Exemplo 5 | B7: (19) 90000-0006 | D7: Campinas | E7: Instagram | F7: =IF(A7="","",COUNTIF(Trabalhos!$C$2:$C$1001,A7)) -> 1 | G7: =IF(A7="","",SUMIFS(Trabalhos!$G$2:$G$1001,Trabalhos!$C$2:$C$1001,A7)) -> 750 | H7: EXEMPLO
A8: Cliente Exemplo 6 | B8: (19) 90000-0007 | D8: Sumaré | E8: Google | F8: =IF(A8="","",COUNTIF(Trabalhos!$C$2:$C$1001,A8)) -> 1 | G8: =IF(A8="","",SUMIFS(Trabalhos!$G$2:$G$1001,Trabalhos!$C$2:$C$1001,A8)) -> 3900 | H8: EXEMPLO
A9: Cliente Exemplo 7 | B9: (19) 90000-0008 | D9: Campinas | E9: Indicação | F9: =IF(A9="","",COUNTIF(Trabalhos!$C$2:$C$1001,A9)) -> 1 | G9: =IF(A9="","",SUMIFS(Trabalhos!$G$2:$G$1001,Trabalhos!$C$2:$C$1001,A9)) -> 2400 | H9: EXEMPLO
A10: Cliente Exemplo 8 | B10: (19) 90000-0009 | D10: Jaguariúna | E10: Instagram | F10: =IF(A10="","",COUNTIF(Trabalhos!$C$2:$C$1001,A10)) -> 1 | G10: =IF(A10="","",SUMIFS(Trabalhos!$G$2:$G$1001,Trabalhos!$C$2:$C$1001,A10)) -> 5600 | H10: EXEMPLO
A11: Cliente Exemplo 9 | B11: (19) 90000-0010 | D11: Campinas | E11: Indicação | F11: =IF(A11="","",COUNTIF(Trabalhos!$C$2:$C$1001,A11)) -> 1 | G11: =IF(A11="","",SUMIFS(Trabalhos!$G$2:$G$1001,Trabalhos!$C$2:$C$1001,A11)) -> 1100 | H11: EXEMPLO
A12: Empresa Exemplo 2 | B12: (19) 90000-0011 | D12: Paulínia | E12: Instagram | F12: =IF(A12="","",COUNTIF(Trabalhos!$C$2:$C$1001,A12)) -> 1 | G12: =IF(A12="","",SUMIFS(Trabalhos!$G$2:$G$1001,Trabalhos!$C$2:$C$1001,A12)) -> 2800 | H12: EXEMPLO
A13: Cliente Exemplo 10 | B13: (19) 90000-0012 | D13: Valinhos | E13: Site | F13: =IF(A13="","",COUNTIF(Trabalhos!$C$2:$C$1001,A13)) -> 1 | G13: =IF(A13="","",SUMIFS(Trabalhos!$G$2:$G$1001,Trabalhos!$C$2:$C$1001,A13)) -> 1300 | H13: EXEMPLO
... A15: Cliente Exemplo 12 | B15: (19) 90000-0014 | D15: Americana | E15: WhatsApp | F15: =IF(A15="","",COUNTIF(Trabalhos!$C$2:$C$1001,A15)) -> 1 | G15: =IF(A15="","",SUMIFS(Trabalhos!$G$2:$G$1001,Trabalhos!$C$2:$C$1001,A15)) -> 1100 | H15: EXEMPLO
F16: =IF(A16="","",COUNTIF(Trabalhos!$C$2:$C$1001,A16)) | G16: =IF(A16="","",SUMIFS(Trabalhos!$G$2:$G$1001,Trabalhos!$C$2:$C$1001,A16))
F17: =IF(A17="","",COUNTIF(Trabalhos!$C$2:$C$1001,A17)) | G17: =IF(A17="","",SUMIFS(Trabalhos!$G$2:$G$1001,Trabalhos!$C$2:$C$1001,A17))
F18: =IF(A18="","",COUNTIF(Trabalhos!$C$2:$C$1001,A18)) | G18: =IF(A18="","",SUMIFS(Trabalhos!$G$2:$G$1001,Trabalhos!$C$2:$C$1001,A18))
F19: =IF(A19="","",COUNTIF(Trabalhos!$C$2:$C$1001,A19)) | G19: =IF(A19="","",SUMIFS(Trabalhos!$G$2:$G$1001,Trabalhos!$C$2:$C$1001,A19))
F20: =IF(A20="","",COUNTIF(Trabalhos!$C$2:$C$1001,A20)) | G20: =IF(A20="","",SUMIFS(Trabalhos!$G$2:$G$1001,Trabalhos!$C$2:$C$1001,A20))
F21: =IF(A21="","",COUNTIF(Trabalhos!$C$2:$C$1001,A21)) | G21: =IF(A21="","",SUMIFS(Trabalhos!$G$2:$G$1001,Trabalhos!$C$2:$C$1001,A21))
F22: =IF(A22="","",COUNTIF(Trabalhos!$C$2:$C$1001,A22)) | G22: =IF(A22="","",SUMIFS(Trabalhos!$G$2:$G$1001,Trabalhos!$C$2:$C$1001,A22))
F23: =IF(A23="","",COUNTIF(Trabalhos!$C$2:$C$1001,A23)) | G23: =IF(A23="","",SUMIFS(Trabalhos!$G$2:$G$1001,Trabalhos!$C$2:$C$1001,A23))
F24: =IF(A24="","",COUNTIF(Trabalhos!$C$2:$C$1001,A24)) | G24: =IF(A24="","",SUMIFS(Trabalhos!$G$2:$G$1001,Trabalhos!$C$2:$C$1001,A24))
F25: =IF(A25="","",COUNTIF(Trabalhos!$C$2:$C$1001,A25)) | G25: =IF(A25="","",SUMIFS(Trabalhos!$G$2:$G$1001,Trabalhos!$C$2:$C$1001,A25))
F26: =IF(A26="","",COUNTIF(Trabalhos!$C$2:$C$1001,A26)) | G26: =IF(A26="","",SUMIFS(Trabalhos!$G$2:$G$1001,Trabalhos!$C$2:$C$1001,A26))
F27: =IF(A27="","",COUNTIF(Trabalhos!$C$2:$C$1001,A27)) | G27: =IF(A27="","",SUMIFS(Trabalhos!$G$2:$G$1001,Trabalhos!$C$2:$C$1001,A27))
... F1001: =IF(A1001="","",COUNTIF(Trabalhos!$C$2:$C$1001,A1001)) | G1001: =IF(A1001="","",SUMIFS(Trabalhos!$G$2:$G$1001,Trabalhos!$C$2:$C$1001,A1001))

Sheet Despesas
A1: Data | B1: Categoria | C1: Descrição | D1: Valor | E1: Forma de pagamento
A2: 46027 | B2: Aplicativos / software | C2: Assinatura app de edição (EXEMPLO) | D2: 60 | E2: Cartão de crédito
A3: 46058 | B3: Aplicativos / software | C3: Assinatura app de edição (EXEMPLO) | D3: 60 | E3: Cartão de crédito
A4: 46086 | B4: Aplicativos / software | C4: Assinatura app de edição (EXEMPLO) | D4: 60 | E4: Cartão de crédito
A5: 46091 | B5: Anúncios / marketing | C5: Impulsionamento Instagram (EXEMPLO) | D5: 200 | E5: Cartão de crédito
A6: 46117 | B6: Aplicativos / software | C6: Assinatura app de edição (EXEMPLO) | D6: 60 | E6: Cartão de crédito
A7: 46147 | B7: Aplicativos / software | C7: Assinatura app de edição (EXEMPLO) | D7: 60 | E7: Cartão de crédito
A8: 46178 | B8: Aplicativos / software | C8: Assinatura app de edição (EXEMPLO) | D8: 60 | E8: Cartão de crédito
A9: 46191 | B9: Cursos | C9: Curso de color grading (EXEMPLO) | D9: 350 | E9: Pix
A10: 46208 | B10: Aplicativos / software | C10: Assinatura app de edição (EXEMPLO) | D10: 60 | E10: Cartão de crédito
A11: 46236 | B11: Manutenção | C11: Limpeza de sensor (EXEMPLO) | D11: 180 | E11: Pix
A12: 46239 | B12: Aplicativos / software | C12: Assinatura app de edição (EXEMPLO) | D12: 60 | E12: Cartão de crédito
A13: 46270 | B13: Aplicativos / software | C13: Assinatura app de edição (EXEMPLO) | D13: 60 | E13: Cartão de crédito
... A15: 46300 | B15: Aplicativos / software | C15: Assinatura app de edição (EXEMPLO) | D15: 60 | E15: Cartão de crédito

Sheet Equipamentos
A1: Equipamento | B1: Categoria | C1: Data da compra | D1: Valor pago | E1: Forma de pagamento | F1: Situação | G1: Observações
A2: Câmera (exemplo) | B2: Câmera | C2: 45915 | D2: 9500 | E2: Parcelado | F2: Em uso | G2: EXEMPLO
A3: Celular (exemplo) | B3: Celular | C3: 45971 | D3: 7000 | E3: Parcelado | F3: Em uso | G3: EXEMPLO
A4: Gimbal (exemplo) | B4: Estabilizador / gimbal | C4: 45971 | D4: 900 | E4: Pix | F4: Em uso | G4: EXEMPLO
A5: Microfone sem fio (exemplo) | B5: Áudio | C5: 46058 | D5: 650 | E5: Cartão de crédito | F5: Em uso | G5: EXEMPLO
A6: Drone (exemplo) | B6: Drone | C6: 46204 | D6: 4200 | E6: Parcelado | F6: Em uso | G6: EXEMPLO

Sheet Listas
A1: Tipos de serviço | B1: Status do orçamento | C1: Forma de pagamento | D1: Categorias de despesa | E1: Categorias de equipamento | F1: Como o cliente conheceu | G1: Situação do equipamento | H1: Meses | J1: Pode adicionar opções nas linhas vazias. Não renomeie "Fechado", "Aguardando" e "Recusado".
A2: Casamento | B2: Aguardando | C2: Pix | D2: Combustível / transporte | E2: Câmera | F2: Instagram | G2: Em uso | H2: Ano inteiro
A3: Aniversário | B3: Fechado | C3: Dinheiro | D3: Alimentação | E3: Celular | F3: Indicação | G3: Vendido | H3: Janeiro
A4: Edição | B4: Recusado | C4: Cartão de crédito | D4: Aplicativos / software | E4: Lente | F4: Site | G4: Quebrado / perdido | H4: Fevereiro
A5: Vídeo institucional | C5: Cartão de débito | D5: Cursos | E5: Estabilizador / gimbal | F5: Google | H5: Março
A6: Storymaker | C6: Parcelado | D6: Anúncios / marketing | E6: Áudio | F6: WhatsApp | H6: Abril
A7: Fotografia | C7: Boleto | D7: Manutenção | E7: Iluminação | F7: Evento | H7: Maio
A8: Chá revelação | C8: Transferência | D8: Acessórios | E8: Drone | F8: Outro | H8: Junho
A9: Outro | D9: Impostos / taxas | E9: Computador | H9: Julho
D10: Outro | E10: Armazenamento | H10: Agosto
E11: Outro | H11: Setembro
H12: Outubro
H13: Novembro
H14: Dezembro
